Workbook

Sheet -> Threat Hunt Result

Sheet Result
A1: _time | B1: index | C1: sourcetype | D1: Source_IP | E1: Destination_IP | F1: Destination_Port | G1: action | H1: Tag_value | I1: Label | J1: Traffic (Outbound/Inbound/Unknown) | K1: Direction Mismatch: Outbound/Inbound Conflict | L1: Follow up action | M1: count | N1: Remark
A2: 2026-07-12T23:56:13.000+0800 | B2: soc_fortinet | C2: fgt_log fortigate_utm | D2: 172.22.100.186 172.22.100.187 172.22.103.184 172.22.99.186 172.22.99.187 192.168.202.31 | E2: 150.171.28.10 | F2: 443 80 | G2: accept allowed pass | H2: 專題-全球風險IP通報 | I2: 僵屍網絡 | J2: =VLOOKUP(E2,'Follow-up Action'!A:C, 3,FALSE) -> outbound | K2: No | L2: =VLOOKUP(E2,'Follow-up Action'!A:D,4,FALSE) -> Block | M2: 19187 | N2: Outbound traffic to external source from HKMA asset detected; No successful inbound traffic from external source
A3: 2026-07-12T23:59:58.000+0800 | B3: soc_fortinet | C3: fgt_log fortigate_utm | D3: 172.22.103.184 172.22.99.186 172.22.99.187 192.168.202.31 | E3: 104.16.80.73 | F3: 443 | G3: accept allowed pass | H3: 惡意事件(B) | I3: 掃描操作 | J3: =VLOOKUP(E3,'Follow-up Action'!A:C, 3,FALSE) -> inbound | K3: Yes | L3: Alert | M3: 15096 | N3: Outbound traffic to external source from HKMA asset detected; No successful inbound traffic from external source
A4: 2026-07-12T23:40:41.000+0800 | B4: soc_fortinet | C4: fgt_log | D4: 172.22.100.187 172.22.99.186 172.22.99.187 192.168.202.31 | E4: 104.16.79.73 | F4: 443 | G4: accept pass | H4: 惡意事件(B) | I4: 掃描操作 | J4: =VLOOKUP(E4,'Follow-up Action'!A:C, 3,FALSE) -> inbound | K4: Yes | L4: Alert | M4: 4465 | N4: Outbound HTTP Traffic via Port 80/443
A5: 2026-07-12T23:24:08.000+0800 | B5: soc_fortinet | C5: fgt_log | D5: 172.22.99.186 172.22.99.187 192.168.202.31 | E5: 155.102.175.140 | F5: 443 80 | G5: accept pass | H5: 惡意事件(B) | I5: 掃描操作 | J5: =VLOOKUP(E5,'Follow-up Action'!A:C, 3,FALSE) -> inbound | K5: Yes | L5: Alert | M5: 3893 | N5: Outbound HTTP Traffic via Port 80/443
A6: 2026-07-12T23:48:28.000+0800 | B6: soc_fortinet | C6: fgt_log | D6: 172.22.99.186 172.22.99.187 192.168.202.31 | E6: 155.102.175.145 | F6: 443 80 | G6: accept pass | H6: 惡意事件(B) | I6: 掃描操作 | J6: =VLOOKUP(E6,'Follow-up Action'!A:C, 3,FALSE) -> inbound | K6: Yes | L6: Alert | M6: 1824 | N6: Outbound HTTP Traffic via Port 80/443
A7: 2026-07-12T23:03:42.000+0800 | B7: soc_fortinet | C7: fgt_log fortigate_utm | D7: 172.22.99.186 172.22.99.187 192.168.202.31 | E7: 155.102.175.144 | F7: 443 80 | G7: accept allowed pass | H7: 惡意事件(B) | I7: 掃描操作 | J7: =VLOOKUP(E7,'Follow-up Action'!A:C, 3,FALSE) -> inbound | K7: Yes | L7: Alert | M7: 1649 | N7: Outbound traffic to external source from HKMA asset detected; No successful inbound traffic from external source
A8: 2026-07-12T23:22:34.000+0800 | B8: soc_fortinet | C8: fgt_log | D8: 172.22.99.186 172.22.99.187 192.168.202.31 | E8: 155.102.175.142 | F8: 443 80 | G8: accept pass | H8: 惡意事件(B) | I8: 掃描操作 | J8: =VLOOKUP(E8,'Follow-up Action'!A:C, 3,FALSE) -> inbound | K8: Yes | L8: Alert | M8: 1628 | N8: Outbound HTTP Traffic via Port 80/443
A9: 2026-07-12T23:46:19.000+0800 | B9: soc_fortinet | C9: fgt_log fortigate_utm | D9: 172.22.99.186 172.22.99.187 192.168.202.31 | E9: 155.102.175.141 | F9: 443 80 | G9: accept allowed pass | H9: 惡意事件(B) | I9: 掃描操作 | J9: =VLOOKUP(E9,'Follow-up Action'!A:C, 3,FALSE) -> inbound | K9: Yes | L9: Alert | M9: 1602 | N9: Outbound traffic to external source from HKMA asset detected; No successful inbound traffic from external source
A10: 2026-07-12T23:57:49.000+0800 | B10: soc_fortinet | C10: fgt_log | D10: 172.22.99.186 172.22.99.187 192.168.202.31 | E10: 155.102.175.143 | F10: 443 80 | G10: accept pass | H10: 惡意事件(B) | I10: 掃描操作 | J10: =VLOOKUP(E10,'Follow-up Action'!A:C, 3,FALSE) -> inbound | K10: Yes | L10: Alert | M10: 1530 | N10: Outbound HTTP Traffic via Port 80/443
A11: 2026-07-10T17:22:04.000+0800 | B11: soc_fortinet | C11: fgt_log | D11: 172.22.99.186 172.22.99.187 | E11: 157.185.135.95 | F11: 443 80 | G11: accept pass | H11: 惡意事件(B) | I11: 掃描操作 | J11: =VLOOKUP(E11,'Follow-up Action'!A:C, 3,FALSE) -> inbound | K11: Yes | L11: Alert | M11: 541 | N11: Outbound HTTP Traffic via Port 80/443
A12: 2026-07-12T23:58:58.000+0800 | B12: soc_fortinet | C12: fgt_log | D12: 216.244.66.243 | E12: 172.22.50.70 | F12: 443 80 | G12: pass | H12: 惡意事件(B) | I12: =VLOOKUP(D12,'Follow-up Action'!A:B,2,FALSE) -> "Exploit", "CyberAttack" | J12: =VLOOKUP(D12,'Follow-up Action'!A:C, 3,FALSE) -> inbound | K12: No | L12: =VLOOKUP(D12,'Follow-up Action'!A:D,4,FALSE) -> Block | M12: 532 | N12: Inbound scanning activity
A13: 2026-07-12T21:13:31.000+0800 | B13: soc_fortinet | C13: fgt_log | D13: 216.244.66.249 | E13: 172.22.50.70 | F13: 443 80 | G13: pass | H13: 惡意事件(B) | I13: =VLOOKUP(D13,'Follow-up Action'!A:B,2,FALSE) -> "Exploit", "CyberAttack" | J13: =VLOOKUP(D13,'Follow-up Action'!A:C, 3,FALSE) -> inbound | K13: No | L13: =VLOOKUP(D13,'Follow-up Action'!A:D,4,FALSE) -> Block | M13: 517 | N13: Inbound scanning activity
A14: 2026-07-12T01:02:06.000+0800 | B14: soc_fortinet | C14: fgt_log | D14: 172.22.99.186 172.22.99.187 | E14: 153.43.128.22 | F14: 443 80 | G14: accept pass | H14: 惡意事件(B) | I14: 掃描操作 | J14: =VLOOKUP(E14,'Follow-up Action'!A:C, 3,FALSE) -> inbound | K14: Yes | L14: Alert | M14: 485 | N14: Outbound HTTP Traffic via Port 80/443
A15: 2026-07-12T22:03:40.000+0800 | B15: soc_fortinet | C15: fgt_log | D15: 216.244.66.200 | E15: 172.22.50.70 | F15: 443 80 | G15: pass | H15: 惡意事件(B) | I15: =VLOOKUP(D15,'Follow-up Action'!A:B,2,FALSE) -> "Exploit", "CyberAttack" | J15: =VLOOKUP(D15,'Follow-up Action'!A:C, 3,FALSE) -> inbound | K15: No | L15: =VLOOKUP(D15,'Follow-up Action'!A:D,4,FALSE) -> Block | M15: 358 | N15: Inbound scanning activity
A16: 2026-07-10T16:16:50.000+0800 | B16: soc_fortinet | C16: fgt_log | D16: 138.199.62.10 | E16: 172.22.99.20 | F16: 443 | G16: pass | H16: 惡意事件(A) | I16: =VLOOKUP(D16,'Follow-up Action'!A:B,2,FALSE) -> 無 | J16: =VLOOKUP(D16,'Follow-up Action'!A:C, 3,FALSE) -> unknown | K16: No | L16: =VLOOKUP(D16,'Follow-up Action'!A:D,4,FALSE) -> Alert | M16: 243 | N16: Inbound scanning activity
A17: 2026-07-10T17:25:46.000+0800 | B17: soc_fortinet | C17: fgt_log | D17: 172.22.99.186 172.22.99.187 | E17: 157.185.135.194 | F17: 443 | G17: accept pass | H17: 惡意事件(B) | I17: 掃描操作 | J17: =VLOOKUP(E17,'Follow-up Action'!A:C, 3,FALSE) -> inbound | K17: Yes | L17: Alert | M17: 243 | N17: Outbound HTTP Traffic via Port 80/443
A18: 2026-07-12T23:45:09.000+0800 | B18: soc_fortinet | C18: fgt_log fortigate_utm | D18: 141.98.83.48 | E18: 172.22.99.90 | F18: 443 80 | G18: allowed pass | H18: DDoS攻擊 | I18: =VLOOKUP(D18,'Follow-up Action'!A:B,2,FALSE) -> DDoS | J18: =VLOOKUP(D18,'Follow-up Action'!A:C, 3,FALSE) -> inbound | K18: No | L18: =VLOOKUP(D18,'Follow-up Action'!A:D,4,FALSE) -> Block | M18: 142 | N18: Inbound traffic to HKMA assets (172.22.99.90) from external source detected; No successful outbound traffic from 172.22.99.90
A19: 2026-07-10T16:21:27.000+0800 | B19: soc_fortinet | C19: fgt_log | D19: 138.199.62.10 | E19: 121.101.172.38 | F19: 53 | G19: accept | H19: 惡意事件(A) | I19: =VLOOKUP(D19,'Follow-up Action'!A:B,2,FALSE) -> 無 | J19: =VLOOKUP(D19,'Follow-up Action'!A:C, 3,FALSE) -> unknown | K19: No | L19: =VLOOKUP(D19,'Follow-up Action'!A:D,4,FALSE) -> Alert | M19: 119 | N19: Inbound DNS traffic to Internet-facing devices via Port 53
A20: 2026-07-12T23:46:33.000+0800 | B20: soc_fortinet | C20: fgt_log fortigate_utm | D20: 141.98.83.48 | E20: 172.22.99.15 | F20: 443 80 | G20: allowed pass | H20: DDoS攻擊 | I20: =VLOOKUP(D20,'Follow-up Action'!A:B,2,FALSE) -> DDoS | J20: =VLOOKUP(D20,'Follow-up Action'!A:C, 3,FALSE) -> inbound | K20: No | L20: =VLOOKUP(D20,'Follow-up Action'!A:D,4,FALSE) -> Block | M20: 111 | N20: Inbound traffic to HKMA assets (172.22.99.15) from external source detected; No successful outbound traffic from 172.22.99.15
A21: 2026-07-12T23:47:12.000+0800 | B21: soc_fortinet | C21: fgt_log fortigate_utm | D21: 141.98.83.48 | E21: 172.22.99.91 | F21: 80 | G21: allowed pass | H21: DDoS攻擊 | I21: =VLOOKUP(D21,'Follow-up Action'!A:B,2,FALSE) -> DDoS | J21: =VLOOKUP(D21,'Follow-up Action'!A:C, 3,FALSE) -> inbound | K21: No | L21: =VLOOKUP(D21,'Follow-up Action'!A:D,4,FALSE) -> Block | M21: 101 | N21: Inbound traffic to HKMA assets (172.22.99.91) from external source detected; No successful outbound traffic from 172.22.99.91
A22: 2026-07-12T15:11:04.000+0800 | B22: soc_fortinet | C22: fgt_log | D22: 172.216.245.31 | E22: 121.101.168.51 | F22: 53 | G22: accept | H22: 惡意事件(B) | I22: =VLOOKUP(D22,'Follow-up Action'!A:B,2,FALSE) -> "Exploit", "CyberAttack" | J22: =VLOOKUP(D22,'Follow-up Action'!A:C, 3,FALSE) -> inbound | K22: No | L22: =VLOOKUP(D22,'Follow-up Action'!A:D,4,FALSE) -> Block | M22: 93 | N22: Inbound DNS traffic to Internet-facing devices via Port 53
A23: 2026-07-10T16:19:50.000+0800 | B23: soc_fortinet | C23: fgt_log | D23: 138.199.62.10 | E23: 121.101.168.51 | F23: 53 | G23: accept | H23: 惡意事件(A) | I23: =VLOOKUP(D23,'Follow-up Action'!A:B,2,FALSE) -> 無 | J23: =VLOOKUP(D23,'Follow-up Action'!A:C, 3,FALSE) -> unknown | K23: No | L23: =VLOOKUP(D23,'Follow-up Action'!A:D,4,FALSE) -> Alert | M23: 92 | N23: Inbound DNS traffic to Internet-facing devices via Port 53
A24: 2026-07-11T17:46:10.000+0800 | B24: soc_fortinet | C24: fgt_log | D24: 172.216.245.31 | E24: 121.101.172.38 | F24: 53 | G24: accept | H24: 惡意事件(B) | I24: =VLOOKUP(D24,'Follow-up Action'!A:B,2,FALSE) -> "Exploit", "CyberAttack" | J24: =VLOOKUP(D24,'Follow-up Action'!A:C, 3,FALSE) -> inbound | K24: No | L24: =VLOOKUP(D24,'Follow-up Action'!A:D,4,FALSE) -> Block | M24: 78 | N24: Inbound DNS traffic to Internet-facing devices via Port 53
A25: 2026-07-06T23:05:47.000+0800 | B25: soc_fortinet | C25: fgt_log fortigate_utm | D25: 141.98.83.48 | E25: 172.22.99.20 | F25: 443 | G25: allowed pass | H25: DDoS攻擊 | I25: =VLOOKUP(D25,'Follow-up Action'!A:B,2,FALSE) -> DDoS | J25: =VLOOKUP(D25,'Follow-up Action'!A:C, 3,FALSE) -> inbound | K25: No | L25: =VLOOKUP(D25,'Follow-up Action'!A:D,4,FALSE) -> Block | M25: 72 | N25: Inbound traffic to HKMA assets (172.22.99.20) from external source detected; No successful outbound traffic from 172.22.99.20
A26: 2026-07-12T02:51:23.000+0800 | B26: soc_fortinet | C26: fgt_log | D26: 47.253.5.130 | E26: 172.22.100.74 | F26: 443 | G26: pass | H26: 惡意事件(B) | I26: =VLOOKUP(D26,'Follow-up Action'!A:B,2,FALSE) -> "Exploit", "CyberAttack" | J26: =VLOOKUP(D26,'Follow-up Action'!A:C, 3,FALSE) -> inbound | K26: No | L26: =VLOOKUP(D26,'Follow-up Action'!A:D,4,FALSE) -> Block | M26: 70 | N26: Inbound scanning activity
A27: 2026-07-11T19:29:14.000+0800 | B27: soc_fortinet | C27: fgt_log | D27: 216.244.66.243 | E27: 172.22.51.70 | F27: 443 80 | G27: pass | H27: 惡意事件(B) | I27: =VLOOKUP(D27,'Follow-up Action'!A:B,2,FALSE) -> "Exploit", "CyberAttack" | J27: =VLOOKUP(D27,'Follow-up Action'!A:C, 3,FALSE) -> inbound | K27: No | L27: =VLOOKUP(D27,'Follow-up Action'!A:D,4,FALSE) -> Block | M27: 69 | N27: Inbound scanning activity
A28: 2026-07-06T23:06:36.000+0800 | B28: soc_fortinet | C28: fgt_log fortigate_utm | D28: 141.98.83.48 | E28: 172.22.99.181 | F28: 443 | G28: allowed pass | H28: DDoS攻擊 | I28: =VLOOKUP(D28,'Follow-up Action'!A:B,2,FALSE) -> DDoS | J28: =VLOOKUP(D28,'Follow-up Action'!A:C, 3,FALSE) -> inbound | K28: No | L28: =VLOOKUP(D28,'Follow-up Action'!A:D,4,FALSE) -> Block | M28: 68 | N28: Inbound traffic to HKMA assets (172.22.99.181) from external source detected; No successful outbound traffic from 172.22.99.181
A29: 2026-07-06T22:46:15.000+0800 | B29: soc_fortinet | C29: fgt_log fortigate_utm | D29: 141.98.83.48 | E29: 172.22.99.183 | F29: 443 | G29: allowed pass | H29: DDoS攻擊 | I29: =VLOOKUP(D29,'Follow-up Action'!A:B,2,FALSE) -> DDoS | J29: =VLOOKUP(D29,'Follow-up Action'!A:C, 3,FALSE) -> inbound | K29: No | L29: =VLOOKUP(D29,'Follow-up Action'!A:D,4,FALSE) -> Block | M29: 66 | N29: Inbound traffic to HKMA assets (172.22.99.183) from external source detected; No successful outbound traffic from 172.22.99.183
A30: 2026-07-10T12:10:44.000+0800 | B30: soc_fortinet | C30: fgt_log | D30: 172.22.99.186 172.22.99.187 | E30: 123.59.186.141 | F30: 443 | G30: pass | H30: DDoS攻擊 | I30: =VLOOKUP(E30,'Follow-up Action'!A:B,2,FALSE) -> DDoS | J30: Inbound | K30: Yes | L30: =VLOOKUP(E30,'Follow-up Action'!A:D,4,FALSE) -> Alert | M30: 63 | N30: Outbound HTTP Traffic via Port 80/443
A31: 2026-07-09T22:09:08.000+0800 | B31: soc_fortinet | C31: fgt_log | D31: 47.253.5.130 | E31: 172.22.99.76 | F31: 443 | G31: pass | H31: 惡意事件(B) | I31: =VLOOKUP(D31,'Follow-up Action'!A:B,2,FALSE) -> "Exploit", "CyberAttack" | J31: =VLOOKUP(D31,'Follow-up Action'!A:C, 3,FALSE) -> inbound | K31: No | L31: =VLOOKUP(D31,'Follow-up Action'!A:D,4,FALSE) -> Block | M31: 62 | N31: Inbound scanning activity
A32: 2026-07-11T05:25:45.000+0800 | B32: soc_fortinet | C32: fgt_log | D32: 216.57.110.81 | E32: 172.22.99.15 | F32: 443 | G32: pass | H32: 惡意事件(B) | I32: =VLOOKUP(D32,'Follow-up Action'!A:B,2,FALSE) -> "Exploit", "CyberAttack" | J32: =VLOOKUP(D32,'Follow-up Action'!A:C, 3,FALSE) -> inbound | K32: No | L32: =VLOOKUP(D32,'Follow-up Action'!A:D,4,FALSE) -> Block | M32: 61 | N32: Inbound scanning activity
A33: 2026-07-12T20:28:55.000+0800 | B33: soc_fortinet | C33: fgt_log | D33: 47.251.53.147 | E33: 172.22.100.23 | F33: 443 | G33: pass | H33: 惡意事件(B) | I33: =VLOOKUP(D33,'Follow-up Action'!A:B,2,FALSE) -> "Exploit", "CyberAttack" | J33: =VLOOKUP(D33,'Follow-up Action'!A:C, 3,FALSE) -> inbound | K33: No | L33: =VLOOKUP(D33,'Follow-up Action'!A:D,4,FALSE) -> Block | M33: 56 | N33: Inbound scanning activity
A34: 2026-07-09T15:59:24.000+0800 | B34: soc_fortinet | C34: fgt_log | D34: 172.22.100.187 172.22.99.186 172.22.99.187 | E34: 23.33.92.22 | F34: 443 80 | G34: accept pass | H34: 惡意事件(A) | I34: 無 | J34: =VLOOKUP(E34,'Follow-up Action'!A:C, 3,FALSE) -> unknown | K34: No | L34: =VLOOKUP(E34,'Follow-up Action'!A:D,4,FALSE) -> Alert | M34: 52 | N34: Outbound HTTP Traffic via Port 80/443
A35: 2026-07-12T23:36:13.000+0800 | B35: soc_fortinet | C35: fgt_log | D35: 66.249.68.164 | E35: 172.22.50.70 | F35: 443 80 | G35: pass | H35: 惡意事件(B) | I35: =VLOOKUP(D35,'Follow-up Action'!A:B,2,FALSE) -> "Exploit", "CyberAttack" | J35: =VLOOKUP(D35,'Follow-up Action'!A:C, 3,FALSE) -> inbound | K35: No | L35: =VLOOKUP(D35,'Follow-up Action'!A:D,4,FALSE) -> Block | M35: 50 | N35: Inbound scanning activity
A36: 2026-07-12T23:36:14.000+0800 | B36: soc_fortinet | C36: fgt_log | D36: 66.249.68.165 | E36: 172.22.50.70 | F36: 443 80 | G36: pass | H36: 惡意事件(B) | I36: =VLOOKUP(D36,'Follow-up Action'!A:B,2,FALSE) -> "Exploit", "CyberAttack" | J36: =VLOOKUP(D36,'Follow-up Action'!A:C, 3,FALSE) -> inbound | K36: No | L36: =VLOOKUP(D36,'Follow-up Action'!A:D,4,FALSE) -> Block | M36: 50 | N36: Inbound scanning activity
A37: 2026-07-11T17:43:08.000+0800 | B37: soc_fortinet | C37: fgt_log | D37: 172.216.245.31 | E37: 172.22.99.20 | F37: 443 | G37: pass | H37: 惡意事件(B) | I37: =VLOOKUP(D37,'Follow-up Action'!A:B,2,FALSE) -> "Exploit", "CyberAttack" | J37: =VLOOKUP(D37,'Follow-up Action'!A:C, 3,FALSE) -> inbound | K37: No | L37: =VLOOKUP(D37,'Follow-up Action'!A:D,4,FALSE) -> Block | M37: 45 | N37: Inbound scanning activity
A38: 2026-07-10T05:04:12.000+0800 | B38: soc_fortinet | C38: fgt_log | D38: 47.253.5.130 | E38: 172.22.100.181 | F38: 443 | G38: pass | H38: 惡意事件(B) | I38: =VLOOKUP(D38,'Follow-up Action'!A:B,2,FALSE) -> "Exploit", "CyberAttack" | J38: =VLOOKUP(D38,'Follow-up Action'!A:C, 3,FALSE) -> inbound | K38: No | L38: =VLOOKUP(D38,'Follow-up Action'!A:D,4,FALSE) -> Block | M38: 45 | N38: Inbound scanning activity
A39: 2026-07-11T06:56:05.000+0800 | B39: soc_fortinet | C39: fgt_log | D39: 86.54.31.38 | E39: 172.22.99.178 | F39: 443 | G39: pass | H39: 惡意事件(B) | I39: =VLOOKUP(D39,'Follow-up Action'!A:B,2,FALSE) -> "Exploit", "CyberAttack" | J39: =VLOOKUP(D39,'Follow-up Action'!A:C, 3,FALSE) -> inbound | K39: No | L39: =VLOOKUP(D39,'Follow-up Action'!A:D,4,FALSE) -> Block | M39: 45 | N39: Inbound scanning activity
A40: 2026-07-12T16:55:28.000+0800 | B40: soc_fortinet | C40: fgt_log | D40: 144.126.215.119 | E40: 172.22.100.76 | F40: 443 | G40: pass | H40: 惡意事件(B) | I40: =VLOOKUP(D40,'Follow-up Action'!A:B,2,FALSE) -> "Exploit", "CyberAttack" | J40: =VLOOKUP(D40,'Follow-up Action'!A:C, 3,FALSE) -> inbound | K40: No | L40: =VLOOKUP(D40,'Follow-up Action'!A:D,4,FALSE) -> Block | M40: 44 | N40: Inbound scanning activity
A41: 2026-07-06T22:48:18.000+0800 | B41: soc_fortinet | C41: fgt_log fortigate_utm | D41: 141.98.83.48 | E41: 172.22.99.77 | F41: 443 | G41: allowed pass | H41: DDoS攻擊 | I41: =VLOOKUP(D41,'Follow-up Action'!A:B,2,FALSE) -> DDoS | J41: =VLOOKUP(D41,'Follow-up Action'!A:C, 3,FALSE) -> inbound | K41: No | L41: =VLOOKUP(D41,'Follow-up Action'!A:D,4,FALSE) -> Block | M41: 41 | N41: Inbound traffic to HKMA assets (172.22.99.77) from external source detected; No successful outbound traffic from 172.22.99.77
A42: 2026-07-10T05:13:52.000+0800 | B42: soc_fortinet | C42: fgt_log | D42: 152.32.133.102 | E42: 172.22.99.79 | F42: 443 | G42: pass | H42: 惡意事件(B) | I42: =VLOOKUP(D42,'Follow-up Action'!A:B,2,FALSE) -> "Exploit", "CyberAttack" | J42: =VLOOKUP(D42,'Follow-up Action'!A:C, 3,FALSE) -> inbound | K42: No | L42: =VLOOKUP(D42,'Follow-up Action'!A:D,4,FALSE) -> Block | M42: 41 | N42: Inbound scanning activity
A43: 2026-07-06T23:09:06.000+0800 | B43: soc_fortinet | C43: fgt_log fortigate_utm | D43: 141.98.83.48 | E43: 172.22.99.124 | F43: 443 | G43: allowed pass | H43: DDoS攻擊 | I43: =VLOOKUP(D43,'Follow-up Action'!A:B,2,FALSE) -> DDoS | J43: =VLOOKUP(D43,'Follow-up Action'!A:C, 3,FALSE) -> inbound | K43: No | L43: =VLOOKUP(D43,'Follow-up Action'!A:D,4,FALSE) -> Block | M43: 40 | N43: Inbound traffic to HKMA assets (172.22.99.124) from external source detected; No successful outbound traffic from 172.22.99.124
A44: 2026-07-06T23:06:43.000+0800 | B44: soc_fortinet | C44: fgt_log fortigate_utm | D44: 141.98.83.48 | E44: 172.22.99.182 | F44: 443 | G44: allowed pass | H44: DDoS攻擊 | I44: =VLOOKUP(D44,'Follow-up Action'!A:B,2,FALSE) -> DDoS | J44: =VLOOKUP(D44,'Follow-up Action'!A:C, 3,FALSE) -> inbound | K44: No | L44: =VLOOKUP(D44,'Follow-up Action'!A:D,4,FALSE) -> Block | M44: 40 | N44: Inbound traffic to HKMA assets (172.22.99.182) from external source detected; No successful outbound traffic from 172.22.99.182
A45: 2026-07-12T00:11:56.000+0800 | B45: soc_fortinet | C45: fgt_log | D45: 47.251.53.147 | E45: 172.22.100.15 | F45: 443 | G45: pass | H45: 惡意事件(B) | I45: =VLOOKUP(D45,'Follow-up Action'!A:B,2,FALSE) -> "Exploit", "CyberAttack" | J45: =VLOOKUP(D45,'Follow-up Action'!A:C, 3,FALSE) -> inbound | K45: No | L45: =VLOOKUP(D45,'Follow-up Action'!A:D,4,FALSE) -> Block | M45: 39 | N45: Inbound scanning activity
A46: 2026-07-06T23:06:44.000+0800 | B46: soc_fortinet | C46: fgt_log fortigate_utm | D46: 141.98.83.48 | E46: 172.22.99.23 | F46: 443 | G46: allowed pass | H46: DDoS攻擊 | I46: =VLOOKUP(D46,'Follow-up Action'!A:B,2,FALSE) -> DDoS | J46: =VLOOKUP(D46,'Follow-up Action'!A:C, 3,FALSE) -> inbound | K46: No | L46: =VLOOKUP(D46,'Follow-up Action'!A:D,4,FALSE) -> Block | M46: 38 | N46: Inbound traffic to HKMA assets (172.22.99.23) from external source detected; No successful outbound traffic from 172.22.99.23
A47: 2026-07-10T08:35:54.000+0800 | B47: soc_fortinet | C47: fgt_log fortigate_utm | D47: 66.132.172.131 | E47: 172.22.100.29 | F47: 8443 | G47: allowed pass | H47: 惡意事件(B) | I47: =VLOOKUP(D47,'Follow-up Action'!A:B,2,FALSE) -> TCP轉發,應用操作,WEB訪問,TCP連接 | J47: =VLOOKUP(D47,'Follow-up Action'!A:C, 3,FALSE) -> outbound | K47: Yes | L47: Alert | M47: 38 | N47: Inbound traffic to HKMA assets (172.22.100.29) from external source detected; No successful outbound traffic from 172.22.100.29
A48: 2026-07-06T21:43:09.000+0800 | B48: soc_fortinet | C48: fgt_log fortigate_utm | D48: 141.98.83.48 | E48: 172.22.97.84 | F48: 443 | G48: allowed pass | H48: DDoS攻擊 | I48: =VLOOKUP(D48,'Follow-up Action'!A:B,2,FALSE) -> DDoS | J48: =VLOOKUP(D48,'Follow-up Action'!A:C, 3,FALSE) -> inbound | K48: No | L48: =VLOOKUP(D48,'Follow-up Action'!A:D,4,FALSE) -> Block | M48: 37 | N48: Inbound traffic to HKMA assets (172.22.97.84) from external source detected; No successful outbound traffic from 172.22.97.84
A49: 2026-07-06T22:47:34.000+0800 | B49: soc_fortinet | C49: fgt_log fortigate_utm | D49: 141.98.83.48 | E49: 172.22.99.178 | F49: 443 | G49: allowed pass | H49: DDoS攻擊 | I49: =VLOOKUP(D49,'Follow-up Action'!A:B,2,FALSE) -> DDoS | J49: =VLOOKUP(D49,'Follow-up Action'!A:C, 3,FALSE) -> inbound | K49: No | L49: =VLOOKUP(D49,'Follow-up Action'!A:D,4,FALSE) -> Block | M49: 36 | N49: Inbound traffic to HKMA assets (172.22.99.178) from external source detected; No successful outbound traffic from 172.22.99.178
A50: 2026-07-06T22:25:48.000+0800 | B50: soc_fortinet | C50: fgt_log fortigate_utm | D50: 141.98.83.48 | E50: 172.22.100.114 | F50: 443 | G50: allowed pass | H50: DDoS攻擊 | I50: =VLOOKUP(D50,'Follow-up Action'!A:B,2,FALSE) -> DDoS | J50: =VLOOKUP(D50,'Follow-up Action'!A:C, 3,FALSE) -> inbound | K50: No | L50: =VLOOKUP(D50,'Follow-up Action'!A:D,4,FALSE) -> Block | M50: 35 | N50: Inbound traffic to HKMA assets (172.22.100.114) from external source detected; No successful outbound traffic from 172.22.100.114
A51: 2026-07-08T22:38:59.000+0800 | B51: soc_fortinet | C51: fgt_log | D51: 45.148.10.62 | E51: 172.22.99.15 | F51: 443 | G51: pass | H51: 惡意事件(B) | I51: =VLOOKUP(D51,'Follow-up Action'!A:B,2,FALSE) -> "Exploit", "CyberAttack" | J51: =VLOOKUP(D51,'Follow-up Action'!A:C, 3,FALSE) -> inbound | K51: No | L51: =VLOOKUP(D51,'Follow-up Action'!A:D,4,FALSE) -> Block | M51: 35 | N51: Inbound scanning activity
A52: 2026-07-12T19:46:28.000+0800 | B52: soc_fortinet | C52: fgt_log | D52: 47.251.53.147 | E52: 172.22.99.24 | F52: 443 8443 | G52: pass | H52: 惡意事件(B) | I52: =VLOOKUP(D52,'Follow-up Action'!A:B,2,FALSE) -> "Exploit", "CyberAttack" | J52: =VLOOKUP(D52,'Follow-up Action'!A:C, 3,FALSE) -> inbound | K52: No | L52: =VLOOKUP(D52,'Follow-up Action'!A:D,4,FALSE) -> Block | M52: 34 | N52: Inbound scanning activity
A53: 2026-07-06T13:37:39.000+0800 | B53: soc_fortinet | C53: fgt_log fortigate_utm | D53: 66.132.186.182 | E53: 172.22.99.29 | F53: 8443 | G53: allowed pass | H53: 惡意事件(B) | I53: =VLOOKUP(D53,'Follow-up Action'!A:B,2,FALSE) -> TCP轉發,HTTP訪問,服務訪問,應用操作,TCP連接 | J53: =VLOOKUP(D53,'Follow-up Action'!A:C, 3,FALSE) -> outbound | K53: Yes | L53: Alert | M53: 31 | N53: Inbound traffic to HKMA assets (172.22.99.29) from external source detected; No successful outbound traffic from 172.22.99.29
A54: 2026-07-11T20:33:30.000+0800 | B54: soc_fortinet | C54: fgt_log | D54: 216.244.66.249 | E54: 172.22.51.70 | F54: 443 80 | G54: pass | H54: 惡意事件(B) | I54: =VLOOKUP(D54,'Follow-up Action'!A:B,2,FALSE) -> "Exploit", "CyberAttack" | J54: =VLOOKUP(D54,'Follow-up Action'!A:C, 3,FALSE) -> inbound | K54: No | L54: =VLOOKUP(D54,'Follow-up Action'!A:D,4,FALSE) -> Block | M54: 31 | N54: Inbound scanning activity
A55: 2026-07-12T13:10:15.000+0800 | B55: soc_fortinet | C55: fgt_log | D55: 47.251.53.147 | E55: 172.22.100.114 | F55: 443 | G55: pass | H55: 惡意事件(B) | I55: =VLOOKUP(D55,'Follow-up Action'!A:B,2,FALSE) -> "Exploit", "CyberAttack" | J55: =VLOOKUP(D55,'Follow-up Action'!A:C, 3,FALSE) -> inbound | K55: No | L55: =VLOOKUP(D55,'Follow-up Action'!A:D,4,FALSE) -> Block | M55: 31 | N55: Inbound scanning activity
A56: 2026-07-11T16:59:42.000+0800 | B56: soc_fortinet | C56: fgt_log | D56: 47.251.53.147 | E56: 172.22.100.74 | F56: 443 | G56: pass | H56: 惡意事件(B) | I56: =VLOOKUP(D56,'Follow-up Action'!A:B,2,FALSE) -> "Exploit", "CyberAttack" | J56: =VLOOKUP(D56,'Follow-up Action'!A:C, 3,FALSE) -> inbound | K56: No | L56: =VLOOKUP(D56,'Follow-up Action'!A:D,4,FALSE) -> Block | M56: 31 | N56: Inbound scanning activity
A57: 2026-07-06T08:48:04.000+0800 | B57: soc_fortinet | C57: fgt_log | D57: 185.225.234.192 | E57: 121.101.172.38 | F57: 53 | G57: accept | H57: 惡意事件(A) | I57: =VLOOKUP(D57,'Follow-up Action'!A:B,2,FALSE) -> 無 | J57: =VLOOKUP(D57,'Follow-up Action'!A:C, 3,FALSE) -> unknown | K57: No | L57: =VLOOKUP(D57,'Follow-up Action'!A:D,4,FALSE) -> Alert | M57: 31 | N57: Inbound DNS traffic to Internet-facing devices via Port 53
A58: 2026-07-10T12:00:20.000+0800 | B58: soc_fortinet | C58: fgt_log | D58: 172.22.99.186 172.22.99.187 | E58: 13.248.169.48 | F58: 443 80 | G58: pass | H58: 專題-全球風險IP通報 | I58: 僵屍網絡 | J58: =VLOOKUP(E58,'Follow-up Action'!A:C, 3,FALSE) -> outbound | K58: No | L58: =VLOOKUP(E58,'Follow-up Action'!A:D,4,FALSE) -> Block | M58: 31 | N58: Outbound HTTP Traffic via Port 80/443
A59: 2026-07-06T22:46:50.000+0800 | B59: soc_fortinet | C59: fgt_log fortigate_utm | D59: 141.98.83.48 | E59: 172.22.97.85 | F59: 443 | G59: allowed pass | H59: DDoS攻擊 | I59: =VLOOKUP(D59,'Follow-up Action'!A:B,2,FALSE) -> DDoS | J59: =VLOOKUP(D59,'Follow-up Action'!A:C, 3,FALSE) -> inbound | K59: No | L59: =VLOOKUP(D59,'Follow-up Action'!A:D,4,FALSE) -> Block | M59: 30 | N59: Inbound traffic to HKMA assets (172.22.97.85) from external source detected; No successful outbound traffic from 172.22.97.85
A60: 2026-07-06T23:06:54.000+0800 | B60: soc_fortinet | C60: fgt_log fortigate_utm | D60: 141.98.83.48 | E60: 172.22.99.125 | F60: 443 | G60: allowed pass | H60: DDoS攻擊 | I60: =VLOOKUP(D60,'Follow-up Action'!A:B,2,FALSE) -> DDoS | J60: =VLOOKUP(D60,'Follow-up Action'!A:C, 3,FALSE) -> inbound | K60: No | L60: =VLOOKUP(D60,'Follow-up Action'!A:D,4,FALSE) -> Block | M60: 30 | N60: Inbound traffic to HKMA assets (172.22.99.125) from external source detected; No successful outbound traffic from 172.22.99.125
A61: 2026-07-12T14:10:07.000+0800 | B61: soc_fortinet | C61: fgt_log fortigate_utm | D61: 66.132.172.138 | E61: 172.22.97.89 | F61: 8443 | G61: allowed pass | H61: 惡意事件(B) | I61: =VLOOKUP(D61,'Follow-up Action'!A:B,2,FALSE) -> TCP轉發,應用操作,WEB訪問,服務訪問 | J61: =VLOOKUP(D61,'Follow-up Action'!A:C, 3,FALSE) -> outbound | K61: Yes | L61: Alert | M61: 30 | N61: Inbound traffic to HKMA assets (172.22.97.89) from external source detected; No successful outbound traffic from 172.22.97.89
A62: 2026-07-12T03:29:08.000+0800 | B62: soc_fortinet | C62: fgt_log | D62: 47.251.53.147 | E62: 172.22.100.178 | F62: 443 | G62: pass | H62: 惡意事件(B) | I62: =VLOOKUP(D62,'Follow-up Action'!A:B,2,FALSE) -> "Exploit", "CyberAttack" | J62: =VLOOKUP(D62,'Follow-up Action'!A:C, 3,FALSE) -> inbound | K62: No | L62: =VLOOKUP(D62,'Follow-up Action'!A:D,4,FALSE) -> Block | M62: 30 | N62: Inbound scanning activity
A63: 2026-07-12T11:13:57.000+0800 | B63: soc_fortinet | C63: fgt_log | D63: 93.123.109.214 | E63: 172.22.100.178 | F63: 443 | G63: pass | H63: 惡意事件(B) | I63: =VLOOKUP(D63,'Follow-up Action'!A:B,2,FALSE) -> "Exploit", "CyberAttack" | J63: =VLOOKUP(D63,'Follow-up Action'!A:C, 3,FALSE) -> inbound | K63: No | L63: =VLOOKUP(D63,'Follow-up Action'!A:D,4,FALSE) -> Block | M63: 30 | N63: Inbound scanning activity
A64: 2026-07-11T02:35:25.000+0800 | B64: soc_fortinet | C64: fgt_log | D64: 172.22.99.186 172.22.99.187 | E64: 43.159.107.113 | F64: 443 80 | G64: accept pass | H64: 惡意事件(B) | I64: 掃描操作 | J64: =VLOOKUP(E64,'Follow-up Action'!A:C, 3,FALSE) -> inbound | K64: Yes | L64: Alert | M64: 30 | N64: Outbound HTTP Traffic via Port 80/443
A65: 2026-07-06T22:45:34.000+0800 | B65: soc_fortinet | C65: fgt_log fortigate_utm | D65: 141.98.83.48 | E65: 172.22.99.76 | F65: 443 | G65: allowed pass | H65: DDoS攻擊 | I65: =VLOOKUP(D65,'Follow-up Action'!A:B,2,FALSE) -> DDoS | J65: =VLOOKUP(D65,'Follow-up Action'!A:C, 3,FALSE) -> inbound | K65: No | L65: =VLOOKUP(D65,'Follow-up Action'!A:D,4,FALSE) -> Block | M65: 29 | N65: Inbound traffic to HKMA assets (172.22.99.76) from external source detected; No successful outbound traffic from 172.22.99.76
A66: 2026-07-10T03:43:51.000+0800 | B66: soc_fortinet | C66: fgt_log fortigate_utm | D66: 66.132.224.93 | E66: 172.22.99.30 | F66: 8443 | G66: allowed pass | H66: 惡意事件(B) | I66: =VLOOKUP(D66,'Follow-up Action'!A:B,2,FALSE) -> TCP轉發,WEB訪問,應用操作,服務訪問 | J66: =VLOOKUP(D66,'Follow-up Action'!A:C, 3,FALSE) -> outbound | K66: Yes | L66: Alert | M66: 29 | N66: Inbound traffic to HKMA assets (172.22.99.30) from external source detected; No successful outbound traffic from 172.22.99.30
A67: 2026-07-12T10:48:27.000+0800 | B67: soc_fortinet | C67: fgt_log | D67: 93.123.109.214 | E67: 172.22.99.15 | F67: 443 80 | G67: pass | H67: 惡意事件(B) | I67: =VLOOKUP(D67,'Follow-up Action'!A:B,2,FALSE) -> "Exploit", "CyberAttack" | J67: =VLOOKUP(D67,'Follow-up Action'!A:C, 3,FALSE) -> inbound | K67: No | L67: =VLOOKUP(D67,'Follow-up Action'!A:D,4,FALSE) -> Block | M67: 29 | N67: Inbound scanning activity
A68: 2026-07-10T08:00:58.000+0800 | B68: soc_fortinet | C68: fgt_log | D68: 107.150.117.187 | E68: 172.22.100.29 | F68: 8443 | G68: pass | H68: 惡意事件(B) | I68: =VLOOKUP(D68,'Follow-up Action'!A:B,2,FALSE) -> "Exploit", "CyberAttack" | J68: =VLOOKUP(D68,'Follow-up Action'!A:C, 3,FALSE) -> inbound | K68: No | L68: =VLOOKUP(D68,'Follow-up Action'!A:D,4,FALSE) -> Block | M68: 27 | N68: Inbound scanning activity
A69: 2026-07-12T03:06:04.000+0800 | B69: soc_fortinet | C69: fgt_log | D69: 44.247.181.228 | E69: 172.22.98.85 | F69: 443 | G69: pass | H69: 惡意事件(B) | I69: =VLOOKUP(D69,'Follow-up Action'!A:B,2,FALSE) -> "Exploit", "CyberAttack" | J69: =VLOOKUP(D69,'Follow-up Action'!A:C, 3,FALSE) -> inbound | K69: No | L69: =VLOOKUP(D69,'Follow-up Action'!A:D,4,FALSE) -> Block | M69: 27 | N69: Inbound scanning activity
A70: 2026-07-12T15:05:02.000+0800 | B70: soc_fortinet | C70: fgt_log | D70: 47.251.53.147 | E70: 172.22.99.29 | F70: 8443 | G70: pass | H70: 惡意事件(B) | I70: =VLOOKUP(D70,'Follow-up Action'!A:B,2,FALSE) -> "Exploit", "CyberAttack" | J70: =VLOOKUP(D70,'Follow-up Action'!A:C, 3,FALSE) -> inbound | K70: No | L70: =VLOOKUP(D70,'Follow-up Action'!A:D,4,FALSE) -> Block | M70: 27 | N70: Inbound scanning activity
A71: 2026-07-06T09:03:08.000+0800 | B71: soc_fortinet | C71: fgt_log | D71: 185.225.234.192 | E71: 121.101.168.51 | F71: 53 | G71: accept | H71: 惡意事件(A) | I71: =VLOOKUP(D71,'Follow-up Action'!A:B,2,FALSE) -> 無 | J71: =VLOOKUP(D71,'Follow-up Action'!A:C, 3,FALSE) -> unknown | K71: No | L71: =VLOOKUP(D71,'Follow-up Action'!A:D,4,FALSE) -> Alert | M71: 27 | N71: Inbound DNS traffic to Internet-facing devices via Port 53
A72: 2026-07-12T23:38:17.000+0800 | B72: soc_fortinet | C72: fgt_log | D72: 66.249.68.165 | E72: 202.128.237.81 | F72: 443 80 | G72: accept | H72: 惡意事件(B) | I72: =VLOOKUP(D72,'Follow-up Action'!A:B,2,FALSE) -> "Exploit", "CyberAttack" | J72: =VLOOKUP(D72,'Follow-up Action'!A:C, 3,FALSE) -> inbound | K72: No | L72: =VLOOKUP(D72,'Follow-up Action'!A:D,4,FALSE) -> Block | M72: 26 | N72: Inbound HTTP/HTTPS traffic to Internet-facing devices via Port 80/443/8443
A73: 2026-07-10T03:17:38.000+0800 | B73: soc_fortinet | C73: fgt_log | D73: 152.32.189.134 | E73: 172.22.97.86 | F73: 443 | G73: pass | H73: 惡意事件(B) | I73: =VLOOKUP(D73,'Follow-up Action'!A:B,2,FALSE) -> "Exploit", "CyberAttack" | J73: =VLOOKUP(D73,'Follow-up Action'!A:C, 3,FALSE) -> inbound | K73: No | L73: =VLOOKUP(D73,'Follow-up Action'!A:D,4,FALSE) -> Block | M73: 26 | N73: Inbound scanning activity
A74: 2026-07-12T18:24:17.000+0800 | B74: soc_fortinet | C74: fgt_log | D74: 47.251.53.147 | E74: 172.22.97.86 | F74: 443 | G74: pass | H74: 惡意事件(B) | I74: =VLOOKUP(D74,'Follow-up Action'!A:B,2,FALSE) -> "Exploit", "CyberAttack" | J74: =VLOOKUP(D74,'Follow-up Action'!A:C, 3,FALSE) -> inbound | K74: No | L74: =VLOOKUP(D74,'Follow-up Action'!A:D,4,FALSE) -> Block | M74: 26 | N74: Inbound scanning activity
A75: 2026-07-12T04:26:35.000+0800 | B75: soc_fortinet | C75: fgt_log | D75: 47.251.53.147 | E75: 172.22.99.15 | F75: 443 | G75: pass | H75: 惡意事件(B) | I75: =VLOOKUP(D75,'Follow-up Action'!A:B,2,FALSE) -> "Exploit", "CyberAttack" | J75: =VLOOKUP(D75,'Follow-up Action'!A:C, 3,FALSE) -> inbound | K75: No | L75: =VLOOKUP(D75,'Follow-up Action'!A:D,4,FALSE) -> Block | M75: 26 | N75: Inbound scanning activity
A76: 2026-07-12T23:38:17.000+0800 | B76: soc_fortinet | C76: fgt_log | D76: 66.249.68.164 | E76: 202.128.237.81 | F76: 443 80 | G76: accept | H76: 惡意事件(B) | I76: =VLOOKUP(D76,'Follow-up Action'!A:B,2,FALSE) -> "Exploit", "CyberAttack" | J76: =VLOOKUP(D76,'Follow-up Action'!A:C, 3,FALSE) -> inbound | K76: No | L76: =VLOOKUP(D76,'Follow-up Action'!A:D,4,FALSE) -> Block | M76: 25 | N76: Inbound HTTP/HTTPS traffic to Internet-facing devices via Port 80/443/8443
A77: 2026-07-11T14:34:41.000+0800 | B77: soc_fortinet | C77: fgt_log fortigate_utm | D77: 66.132.186.199 | E77: 172.22.97.88 | F77: 8443 | G77: allowed pass | H77: 惡意事件(B) | I77: =VLOOKUP(D77,'Follow-up Action'!A:B,2,FALSE) -> TCP轉發,WEB訪問,應用操作,服務訪問 | J77: =VLOOKUP(D77,'Follow-up Action'!A:C, 3,FALSE) -> outbound | K77: Yes | L77: Alert | M77: 25 | N77: Inbound traffic to HKMA assets (172.22.97.88) from external source detected; No successful outbound traffic from 172.22.97.88
A78: 2026-07-12T19:07:26.000+0800 | B78: soc_fortinet | C78: fgt_log | D78: 123.160.223.72 | E78: 172.22.50.70 | F78: 443 80 | G78: pass | H78: 惡意事件(B) | I78: =VLOOKUP(D78,'Follow-up Action'!A:B,2,FALSE) -> "Exploit", "CyberAttack" | J78: =VLOOKUP(D78,'Follow-up Action'!A:C, 3,FALSE) -> inbound | K78: No | L78: =VLOOKUP(D78,'Follow-up Action'!A:D,4,FALSE) -> Block | M78: 25 | N78: Inbound scanning activity
A79: 2026-07-11T14:35:09.000+0800 | B79: soc_fortinet | C79: fgt_log fortigate_utm | D79: 66.132.172.191 | E79: 172.22.97.88 | F79: 8443 | G79: allowed pass | H79: 惡意事件(B) | I79: =VLOOKUP(D79,'Follow-up Action'!A:B,2,FALSE) -> TCP轉發,WEB訪問,服務訪問 | J79: =VLOOKUP(D79,'Follow-up Action'!A:C, 3,FALSE) -> outbound | K79: Yes | L79: Alert | M79: 24 | N79: Inbound traffic to HKMA assets (172.22.97.88) from external source detected; No successful outbound traffic from 172.22.97.88
A80: 2026-07-07T14:47:24.000+0800 | B80: soc_fortinet | C80: fgt_log | D80: 64.62.156.52 | E80: 172.22.99.125 | F80: 443 | G80: pass | H80: 惡意事件(B) | I80: =VLOOKUP(D80,'Follow-up Action'!A:B,2,FALSE) -> "Exploit", "CyberAttack" | J80: =VLOOKUP(D80,'Follow-up Action'!A:C, 3,FALSE) -> inbound | K80: No | L80: =VLOOKUP(D80,'Follow-up Action'!A:D,4,FALSE) -> Block | M80: 24 | N80: Inbound scanning activity
A81: 2026-07-10T20:09:59.000+0800 | B81: soc_fortinet | C81: fgt_log | D81: 65.49.1.38 | E81: 172.22.99.15 | F81: 443 | G81: pass | H81: 惡意事件(B) | I81: =VLOOKUP(D81,'Follow-up Action'!A:B,2,FALSE) -> "Exploit", "CyberAttack" | J81: =VLOOKUP(D81,'Follow-up Action'!A:C, 3,FALSE) -> inbound | K81: No | L81: =VLOOKUP(D81,'Follow-up Action'!A:D,4,FALSE) -> Block | M81: 24 | N81: Inbound scanning activity
A82: 2026-07-12T03:06:04.000+0800 | B82: soc_fortinet | C82: fgt_log | D82: 44.247.181.228 | E82: 172.22.100.20 | F82: 443 | G82: pass | H82: 惡意事件(B) | I82: =VLOOKUP(D82,'Follow-up Action'!A:B,2,FALSE) -> "Exploit", "CyberAttack" | J82: =VLOOKUP(D82,'Follow-up Action'!A:C, 3,FALSE) -> inbound | K82: No | L82: =VLOOKUP(D82,'Follow-up Action'!A:D,4,FALSE) -> Block | M82: 23 | N82: Inbound scanning activity
A83: 2026-07-10T08:01:21.000+0800 | B83: soc_fortinet | C83: fgt_log | D83: 47.251.53.147 | E83: 172.22.100.181 | F83: 443 | G83: pass | H83: 惡意事件(B) | I83: =VLOOKUP(D83,'Follow-up Action'!A:B,2,FALSE) -> "Exploit", "CyberAttack" | J83: =VLOOKUP(D83,'Follow-up Action'!A:C, 3,FALSE) -> inbound | K83: No | L83: =VLOOKUP(D83,'Follow-up Action'!A:D,4,FALSE) -> Block | M83: 23 | N83: Inbound scanning activity
A84: 2026-07-08T10:37:22.000+0800 | B84: soc_fortinet | C84: fgt_log | D84: 66.132.172.135 | E84: 172.22.97.84 | F84: 443 | G84: pass | H84: 惡意事件(B) | I84: =VLOOKUP(D84,'Follow-up Action'!A:B,2,FALSE) -> TCP轉發,應用操作,TCP連接 | J84: =VLOOKUP(D84,'Follow-up Action'!A:C, 3,FALSE) -> unknown | K84: No | L84: =VLOOKUP(D84,'Follow-up Action'!A:D,4,FALSE) -> Alert | M84: 23 | N84: Inbound scanning activity
A85: 2026-07-10T16:45:29.000+0800 | B85: soc_fortinet | C85: fgt_log | D85: 172.22.99.186 192.168.202.31 | E85: 155.102.181.184 | F85: 443 | G85: accept pass | H85: 惡意事件(B) | I85: 掃描操作 | J85: =VLOOKUP(E85,'Follow-up Action'!A:C, 3,FALSE) -> inbound | K85: Yes | L85: Alert | M85: 23 | N85: Outbound HTTP Traffic via Port 80/443
A86: 2026-07-10T07:59:55.000+0800 | B86: soc_fortinet | C86: fgt_log fortigate_utm | D86: 107.150.117.187 | E86: 172.22.100.90 | F86: 8443 | G86: allowed pass | H86: 惡意事件(B) | I86: =VLOOKUP(D86,'Follow-up Action'!A:B,2,FALSE) -> "Exploit", "CyberAttack" | J86: =VLOOKUP(D86,'Follow-up Action'!A:C, 3,FALSE) -> inbound | K86: No | L86: =VLOOKUP(D86,'Follow-up Action'!A:D,4,FALSE) -> Block | M86: 22 | N86: Inbound traffic to HKMA assets (172.22.100.90) from external source detected; No successful outbound traffic from 172.22.100.90
A87: 2026-07-09T02:52:28.000+0800 | B87: soc_fortinet | C87: fgt_log fortigate_utm | D87: 66.132.172.99 | E87: 172.22.99.30 | F87: 8443 | G87: allowed pass | H87: 惡意事件(B) | I87: =VLOOKUP(D87,'Follow-up Action'!A:B,2,FALSE) -> TCP轉發,應用操作,服務訪問 | J87: =VLOOKUP(D87,'Follow-up Action'!A:C, 3,FALSE) -> outbound | K87: Yes | L87: Alert | M87: 22 | N87: Inbound traffic to HKMA assets (172.22.99.30) from external source detected; No successful outbound traffic from 172.22.99.30
A88: 2026-07-11T04:10:34.000+0800 | B88: soc_fortinet | C88: fgt_log fortigate_utm | D88: 66.132.186.195 | E88: 172.22.99.30 | F88: 8443 | G88: allowed pass | H88: 惡意事件(B) | I88: =VLOOKUP(D88,'Follow-up Action'!A:B,2,FALSE) -> TCP轉發,應用操作,服務訪問,HTTP訪問,WEB訪問 | J88: =VLOOKUP(D88,'Follow-up Action'!A:C, 3,FALSE) -> outbound | K88: Yes | L88: Alert | M88: 22 | N88: Inbound traffic to HKMA assets (172.22.99.30) from external source detected; No successful outbound traffic from 172.22.99.30
A89: 2026-07-10T07:56:41.000+0800 | B89: soc_fortinet | C89: fgt_log | D89: 107.150.117.187 | E89: 172.22.98.89 | F89: 8443 | G89: pass | H89: 惡意事件(B) | I89: =VLOOKUP(D89,'Follow-up Action'!A:B,2,FALSE) -> "Exploit", "CyberAttack" | J89: =VLOOKUP(D89,'Follow-up Action'!A:C, 3,FALSE) -> inbound | K89: No | L89: =VLOOKUP(D89,'Follow-up Action'!A:D,4,FALSE) -> Block | M89: 22 | N89: Inbound scanning activity
A90: 2026-07-12T14:12:26.000+0800 | B90: soc_fortinet | C90: fgt_log | D90: 159.138.239.156 | E90: 172.22.50.70 | F90: 446 82 | G90: pass | H90: 惡意事件(B) | I90: =VLOOKUP(D90,'Follow-up Action'!A:B,2,FALSE) -> "Exploit", "CyberAttack" | J90: =VLOOKUP(D90,'Follow-up Action'!A:C, 3,FALSE) -> inbound | K90: No | L90: =VLOOKUP(D90,'Follow-up Action'!A:D,4,FALSE) -> Block | M90: 22 | N90: Inbound scanning activity
A91: 2026-07-10T08:32:24.000+0800 | B91: soc_fortinet | C91: fgt_log | D91: 47.251.53.147 | E91: 172.22.100.20 | F91: 443 | G91: pass | H91: 惡意事件(B) | I91: =VLOOKUP(D91,'Follow-up Action'!A:B,2,FALSE) -> "Exploit", "CyberAttack" | J91: =VLOOKUP(D91,'Follow-up Action'!A:C, 3,FALSE) -> inbound | K91: No | L91: =VLOOKUP(D91,'Follow-up Action'!A:D,4,FALSE) -> Block | M91: 22 | N91: Inbound scanning activity
A92: 2026-07-12T11:50:25.000+0800 | B92: soc_fortinet | C92: fgt_log | D92: 47.251.53.147 | E92: 172.22.98.89 | F92: 8443 | G92: pass | H92: 惡意事件(B) | I92: =VLOOKUP(D92,'Follow-up Action'!A:B,2,FALSE) -> "Exploit", "CyberAttack" | J92: =VLOOKUP(D92,'Follow-up Action'!A:C, 3,FALSE) -> inbound | K92: No | L92: =VLOOKUP(D92,'Follow-up Action'!A:D,4,FALSE) -> Block | M92: 22 | N92: Inbound scanning activity
A93: 2026-07-10T14:28:58.000+0800 | B93: soc_fortinet | C93: fgt_log | D93: 64.62.156.52 | E93: 172.22.99.24 | F93: 443 8443 | G93: pass | H93: 惡意事件(B) | I93: =VLOOKUP(D93,'Follow-up Action'!A:B,2,FALSE) -> "Exploit", "CyberAttack" | J93: =VLOOKUP(D93,'Follow-up Action'!A:C, 3,FALSE) -> inbound | K93: No | L93: =VLOOKUP(D93,'Follow-up Action'!A:D,4,FALSE) -> Block | M93: 22 | N93: Inbound scanning activity
A94: 2026-07-12T09:51:37.000+0800 | B94: soc_fortinet | C94: fgt_log | D94: 93.123.109.214 | E94: 172.22.99.24 | F94: 443 | G94: pass | H94: 惡意事件(B) | I94: =VLOOKUP(D94,'Follow-up Action'!A:B,2,FALSE) -> "Exploit", "CyberAttack" | J94: =VLOOKUP(D94,'Follow-up Action'!A:C, 3,FALSE) -> inbound | K94: No | L94: =VLOOKUP(D94,'Follow-up Action'!A:D,4,FALSE) -> Block | M94: 22 | N94: Inbound scanning activity
A95: 2026-07-08T11:35:32.000+0800 | B95: soc_fortinet | C95: fgt_log fortigate_utm | D95: 66.132.172.135 | E95: 172.22.99.30 | F95: 8443 | G95: allowed pass | H95: 惡意事件(B) | I95: =VLOOKUP(D95,'Follow-up Action'!A:B,2,FALSE) -> TCP轉發,應用操作,TCP連接 | J95: =VLOOKUP(D95,'Follow-up Action'!A:C, 3,FALSE) -> unknown | K95: No | L95: =VLOOKUP(D95,'Follow-up Action'!A:D,4,FALSE) -> Alert | M95: 21 | N95: Inbound traffic to HKMA assets (172.22.99.30) from external source detected; No successful outbound traffic from 172.22.99.30
A96: 2026-07-08T02:07:25.000+0800 | B96: soc_fortinet | C96: fgt_log fortigate_utm | D96: 66.132.172.138 | E96: 172.22.97.88 | F96: 8443 | G96: allowed pass | H96: 惡意事件(B) | I96: =VLOOKUP(D96,'Follow-up Action'!A:B,2,FALSE) -> TCP轉發,應用操作,WEB訪問,服務訪問 | J96: =VLOOKUP(D96,'Follow-up Action'!A:C, 3,FALSE) -> outbound | K96: Yes | L96: Alert | M96: 21 | N96: Inbound traffic to HKMA assets (172.22.97.88) from external source detected; No successful outbound traffic from 172.22.97.88
A97: 2026-07-11T19:45:11.000+0800 | B97: soc_fortinet | C97: fgt_log fortigate_utm | D97: 66.132.172.142 | E97: 172.22.97.84 | F97: 443 | G97: allowed pass | H97: 惡意事件(B) | I97: =VLOOKUP(D97,'Follow-up Action'!A:B,2,FALSE) -> "Exploit", "CyberAttack" | J97: =VLOOKUP(D97,'Follow-up Action'!A:C, 3,FALSE) -> inbound | K97: No | L97: =VLOOKUP(D97,'Follow-up Action'!A:D,4,FALSE) -> Block | M97: 21 | N97: Inbound traffic to HKMA assets (172.22.97.84) from external source detected; No successful outbound traffic from 172.22.97.84
A98: 2026-07-07T11:07:15.000+0800 | B98: soc_fortinet | C98: fgt_log fortigate_utm | D98: 66.132.195.110 | E98: 172.22.99.30 | F98: 8443 | G98: allowed pass | H98: 惡意事件(B) | I98: =VLOOKUP(D98,'Follow-up Action'!A:B,2,FALSE) -> TCP轉發,應用操作,WEB訪問,HTTP訪問 | J98: =VLOOKUP(D98,'Follow-up Action'!A:C, 3,FALSE) -> outbound | K98: Yes | L98: Alert | M98: 21 | N98: Inbound traffic to HKMA assets (172.22.99.30) from external source detected; No successful outbound traffic from 172.22.99.30
A99: 2026-07-10T08:00:43.000+0800 | B99: soc_fortinet | C99: fgt_log | D99: 107.150.117.187 | E99: 172.22.98.88 | F99: 8443 | G99: pass | H99: 惡意事件(B) | I99: =VLOOKUP(D99,'Follow-up Action'!A:B,2,FALSE) -> "Exploit", "CyberAttack" | J99: =VLOOKUP(D99,'Follow-up Action'!A:C, 3,FALSE) -> inbound | K99: No | L99: =VLOOKUP(D99,'Follow-up Action'!A:D,4,FALSE) -> Block | M99: 21 | N99: Inbound scanning activity
A100: 2026-07-09T07:59:16.000+0800 | B100: soc_fortinet | C100: fgt_log | D100: 212.73.148.38 | E100: 172.22.99.181 | F100: 443 | G100: pass | H100: 惡意事件(B) | I100: =VLOOKUP(D100,'Follow-up Action'!A:B,2,FALSE) -> 應用操作,HTTP訪問,TCP連接,TCP轉發,服務訪問,WEB訪問 | J100: =VLOOKUP(D100,'Follow-up Action'!A:C, 3,FALSE) -> outbound | K100: Yes | L100: Alert | M100: 21 | N100: Inbound scanning activity
...

Sheet Follow-up Action
A1: IOC | B1: Label | C1: Traffic (Outbound/Inbound/Unknown) | D1: Follow up action | F1: Label | G1: Traffic (Outbound/Inbound/Unknown) | I1: Classification | J1: Follow up action
A2: 103.40.79.139 | B2: 無 | C2: {=IFERROR( IF(SUMPRODUCT((LEN(B2)-LEN(SUBSTITUTE(B2,$F$2:$F$300,"")))*(($G$2:$G$300)="outbound"))>0,"outbound", IF(SUMPRODUCT((LEN(B2)-LEN(SUBSTITUTE(B2,$F$2:$F$300,"")))*(($G$2:$G$300)="inbound"))>0,"inbound","unknown")), "unknown" )} -> unknown | D2: =VLOOKUP(C2,$I$2:$J$5,2,FALSE) -> Alert | F2: 釣魚網站 | G2: outbound | I2: Inbound | J2: Block
A3: 14.29.236.229 | B3: APT組織：OceanLotus | C3: {=IFERROR( IF(SUMPRODUCT((LEN(B3)-LEN(SUBSTITUTE(B3,$F$2:$F$300,"")))*(($G$2:$G$300)="outbound"))>0,"outbound", IF(SUMPRODUCT((LEN(B3)-LEN(SUBSTITUTE(B3,$F$2:$F$300,"")))*(($G$2:$G$300)="inbound"))>0,"inbound","unknown")), "unknown" )} -> unknown | D3: =VLOOKUP(C3,$I$2:$J$5,2,FALSE) -> Alert | F3: Websafe.Phishing | G3: outbound | I3: Outbound | J3: Block
A4: 103.57.248.171 | B4: 無 | C4: {=IFERROR( IF(SUMPRODUCT((LEN(B4)-LEN(SUBSTITUTE(B4,$F$2:$F$300,"")))*(($G$2:$G$300)="outbound"))>0,"outbound", IF(SUMPRODUCT((LEN(B4)-LEN(SUBSTITUTE(B4,$F$2:$F$300,"")))*(($G$2:$G$300)="inbound"))>0,"inbound","unknown")), "unknown" )} -> unknown | D4: =VLOOKUP(C4,$I$2:$J$5,2,FALSE) -> Alert | F4: Phishing | G4: outbound | I4: Unknown | J4: Alert
A5: 138.199.62.10 | B5: 無 | C5: {=IFERROR( IF(SUMPRODUCT((LEN(B5)-LEN(SUBSTITUTE(B5,$F$2:$F$300,"")))*(($G$2:$G$300)="outbound"))>0,"outbound", IF(SUMPRODUCT((LEN(B5)-LEN(SUBSTITUTE(B5,$F$2:$F$300,"")))*(($G$2:$G$300)="inbound"))>0,"inbound","unknown")), "unknown" )} -> unknown | D5: =VLOOKUP(C5,$I$2:$J$5,2,FALSE) -> Alert | F5: Silver fox | G5: unknown | I5: Direction Mismatch: Outbound/Inbound Conflict | J5: Alert
A6: 118.99.2.23 | B6: 無 | C6: {=IFERROR( IF(SUMPRODUCT((LEN(B6)-LEN(SUBSTITUTE(B6,$F$2:$F$300,"")))*(($G$2:$G$300)="outbound"))>0,"outbound", IF(SUMPRODUCT((LEN(B6)-LEN(SUBSTITUTE(B6,$F$2:$F$300,"")))*(($G$2:$G$300)="inbound"))>0,"inbound","unknown")), "unknown" )} -> unknown | D6: =VLOOKUP(C6,$I$2:$J$5,2,FALSE) -> Alert | F6: OceanLotus | G6: unknown
A7: 149.40.54.75 | B7: 無 | C7: {=IFERROR( IF(SUMPRODUCT((LEN(B7)-LEN(SUBSTITUTE(B7,$F$2:$F$300,"")))*(($G$2:$G$300)="outbound"))>0,"outbound", IF(SUMPRODUCT((LEN(B7)-LEN(SUBSTITUTE(B7,$F$2:$F$300,"")))*(($G$2:$G$300)="inbound"))>0,"inbound","unknown")), "unknown" )} -> unknown | D7: =VLOOKUP(C7,$I$2:$J$5,2,FALSE) -> Alert | F7: Generic Trojan | G7: unknown
A8: 185.225.234.192 | B8: 無 | C8: {=IFERROR( IF(SUMPRODUCT((LEN(B8)-LEN(SUBSTITUTE(B8,$F$2:$F$300,"")))*(($G$2:$G$300)="outbound"))>0,"outbound", IF(SUMPRODUCT((LEN(B8)-LEN(SUBSTITUTE(B8,$F$2:$F$300,"")))*(($G$2:$G$300)="inbound"))>0,"inbound","unknown")), "unknown" )} -> unknown | D8: =VLOOKUP(C8,$I$2:$J$5,2,FALSE) -> Alert | F8: BlackMarket | G8: unknown
A9: 185.225.234.62 | B9: 無 | C9: {=IFERROR( IF(SUMPRODUCT((LEN(B9)-LEN(SUBSTITUTE(B9,$F$2:$F$300,"")))*(($G$2:$G$300)="outbound"))>0,"outbound", IF(SUMPRODUCT((LEN(B9)-LEN(SUBSTITUTE(B9,$F$2:$F$300,"")))*(($G$2:$G$300)="inbound"))>0,"inbound","unknown")), "unknown" )} -> unknown | D9: =VLOOKUP(C9,$I$2:$J$5,2,FALSE) -> Alert | F9: Gh0st | G9: unknown
A10: 156.146.45.194 | B10: 無 | C10: {=IFERROR( IF(SUMPRODUCT((LEN(B10)-LEN(SUBSTITUTE(B10,$F$2:$F$300,"")))*(($G$2:$G$300)="outbound"))>0,"outbound", IF(SUMPRODUCT((LEN(B10)-LEN(SUBSTITUTE(B10,$F$2:$F$300,"")))*(($G$2:$G$300)="inbound"))>0,"inbound","unknown")), "unknown" )} -> unknown | D10: =VLOOKUP(C10,$I$2:$J$5,2,FALSE) -> Alert | F10: SilverFox | G10: unknown
A11: 185.225.234.144 | B11: 無 | C11: {=IFERROR( IF(SUMPRODUCT((LEN(B11)-LEN(SUBSTITUTE(B11,$F$2:$F$300,"")))*(($G$2:$G$300)="outbound"))>0,"outbound", IF(SUMPRODUCT((LEN(B11)-LEN(SUBSTITUTE(B11,$F$2:$F$300,"")))*(($G$2:$G$300)="inbound"))>0,"inbound","unknown")), "unknown" )} -> unknown | D11: =VLOOKUP(C11,$I$2:$J$5,2,FALSE) -> Alert | F11: Botnet | G11: outbound
A12: 38.180.150.40 | B12: APT組織：OceanLotus | C12: {=IFERROR( IF(SUMPRODUCT((LEN(B12)-LEN(SUBSTITUTE(B12,$F$2:$F$300,"")))*(($G$2:$G$300)="outbound"))>0,"outbound", IF(SUMPRODUCT((LEN(B12)-LEN(SUBSTITUTE(B12,$F$2:$F$300,"")))*(($G$2:$G$300)="inbound"))>0,"inbound","unknown")), "unknown" )} -> unknown | D12: =VLOOKUP(C12,$I$2:$J$5,2,FALSE) -> Alert | F12: CnC | G12: outbound
A13: 183.87.124.189 | B13: 無 | C13: {=IFERROR( IF(SUMPRODUCT((LEN(B13)-LEN(SUBSTITUTE(B13,$F$2:$F$300,"")))*(($G$2:$G$300)="outbound"))>0,"outbound", IF(SUMPRODUCT((LEN(B13)-LEN(SUBSTITUTE(B13,$F$2:$F$300,"")))*(($G$2:$G$300)="inbound"))>0,"inbound","unknown")), "unknown" )} -> unknown | D13: =VLOOKUP(C13,$I$2:$J$5,2,FALSE) -> Alert | F13: Scanner | G13: inbound
A14: 192.166.244.113 | B14: 無 | C14: {=IFERROR( IF(SUMPRODUCT((LEN(B14)-LEN(SUBSTITUTE(B14,$F$2:$F$300,"")))*(($G$2:$G$300)="outbound"))>0,"outbound", IF(SUMPRODUCT((LEN(B14)-LEN(SUBSTITUTE(B14,$F$2:$F$300,"")))*(($G$2:$G$300)="inbound"))>0,"inbound","unknown")), "unknown" )} -> unknown | D14: =VLOOKUP(C14,$I$2:$J$5,2,FALSE) -> Alert | F14: CyberAttack | G14: unknown
A15: 192.166.244.79 | B15: 無 | C15: {=IFERROR( IF(SUMPRODUCT((LEN(B15)-LEN(SUBSTITUTE(B15,$F$2:$F$300,"")))*(($G$2:$G$300)="outbound"))>0,"outbound", IF(SUMPRODUCT((LEN(B15)-LEN(SUBSTITUTE(B15,$F$2:$F$300,"")))*(($G$2:$G$300)="inbound"))>0,"inbound","unknown")), "unknown" )} -> unknown | D15: =VLOOKUP(C15,$I$2:$J$5,2,FALSE) -> Alert | F15: Spam | G15: inbound
A16: 203.168.241.141 | B16: 無 | C16: {=IFERROR( IF(SUMPRODUCT((LEN(B16)-LEN(SUBSTITUTE(B16,$F$2:$F$300,"")))*(($G$2:$G$300)="outbound"))>0,"outbound", IF(SUMPRODUCT((LEN(B16)-LEN(SUBSTITUTE(B16,$F$2:$F$300,"")))*(($G$2:$G$300)="inbound"))>0,"inbound","unknown")), "unknown" )} -> unknown | D16: =VLOOKUP(C16,$I$2:$J$5,2,FALSE) -> Alert | F16: BruteForcer | G16: inbound
A17: 43.249.51.79 | B17: 無 | C17: {=IFERROR( IF(SUMPRODUCT((LEN(B17)-LEN(SUBSTITUTE(B17,$F$2:$F$300,"")))*(($G$2:$G$300)="outbound"))>0,"outbound", IF(SUMPRODUCT((LEN(B17)-LEN(SUBSTITUTE(B17,$F$2:$F$300,"")))*(($G$2:$G$300)="inbound"))>0,"inbound","unknown")), "unknown" )} -> unknown | D17: =VLOOKUP(C17,$I$2:$J$5,2,FALSE) -> Alert | F17: Asyncrat | G17: unknown
... A146: 154.23.176.76 | B146: "CnC" | C146: {=IFERROR( IF(SUMPRODUCT((LEN(B146)-LEN(SUBSTITUTE(B146,$F$2:$F$300,"")))*(($G$2:$G$300)="outbound"))>0,"outbound", IF(SUMPRODUCT((LEN(B146)-LEN(SUBSTITUTE(B146,$F$2:$F$300,"")))*(($G$2:$G$300)="inbound"))>0,"inbound","unknown")), "unknown" )} -> outbound | D146: =VLOOKUP(C146,$I$2:$J$5,2,FALSE) -> Block | F146: 無 | G146: unknown
A147: 45.145.228.152 | B147: "Cobaltstrike", "CyberAttack", "CnC" | C147: {=IFERROR( IF(SUMPRODUCT((LEN(B147)-LEN(SUBSTITUTE(B147,$F$2:$F$300,"")))*(($G$2:$G$300)="outbound"))>0,"outbound", IF(SUMPRODUCT((LEN(B147)-LEN(SUBSTITUTE(B147,$F$2:$F$300,"")))*(($G$2:$G$300)="inbound"))>0,"inbound","unknown")), "unknown" )} -> outbound | D147: =VLOOKUP(C147,$I$2:$J$5,2,FALSE) -> Block
A148: 152.32.175.104 | B148: "Exploit", "Scanner" | C148: {=IFERROR( IF(SUMPRODUCT((LEN(B148)-LEN(SUBSTITUTE(B148,$F$2:$F$300,"")))*(($G$2:$G$300)="outbound"))>0,"outbound", IF(SUMPRODUCT((LEN(B148)-LEN(SUBSTITUTE(B148,$F$2:$F$300,"")))*(($G$2:$G$300)="inbound"))>0,"inbound","unknown")), "unknown" )} -> inbound | D148: =VLOOKUP(C148,$I$2:$J$5,2,FALSE) -> Block
A149: 8.218.44.185 | B149: "GoldenEye", "SilverFox" | C149: {=IFERROR( IF(SUMPRODUCT((LEN(B149)-LEN(SUBSTITUTE(B149,$F$2:$F$300,"")))*(($G$2:$G$300)="outbound"))>0,"outbound", IF(SUMPRODUCT((LEN(B149)-LEN(SUBSTITUTE(B149,$F$2:$F$300,"")))*(($G$2:$G$300)="inbound"))>0,"inbound","unknown")), "unknown" )} -> unknown | D149: =VLOOKUP(C149,$I$2:$J$5,2,FALSE) -> Alert
A150: 165.154.20.228 | B150: "Exploit", "Scanner" | C150: {=IFERROR( IF(SUMPRODUCT((LEN(B150)-LEN(SUBSTITUTE(B150,$F$2:$F$300,"")))*(($G$2:$G$300)="outbound"))>0,"outbound", IF(SUMPRODUCT((LEN(B150)-LEN(SUBSTITUTE(B150,$F$2:$F$300,"")))*(($G$2:$G$300)="inbound"))>0,"inbound","unknown")), "unknown" )} -> inbound | D150: =VLOOKUP(C150,$I$2:$J$5,2,FALSE) -> Block
A151: 36.255.220.195 | B151: "Exploit", "Scanner" | C151: {=IFERROR( IF(SUMPRODUCT((LEN(B151)-LEN(SUBSTITUTE(B151,$F$2:$F$300,"")))*(($G$2:$G$300)="outbound"))>0,"outbound", IF(SUMPRODUCT((LEN(B151)-LEN(SUBSTITUTE(B151,$F$2:$F$300,"")))*(($G$2:$G$300)="inbound"))>0,"inbound","unknown")), "unknown" )} -> inbound | D151: =VLOOKUP(C151,$I$2:$J$5,2,FALSE) -> Block
A152: 152.32.226.205 | B152: "Exploit", "Scanner" | C152: {=IFERROR( IF(SUMPRODUCT((LEN(B152)-LEN(SUBSTITUTE(B152,$F$2:$F$300,"")))*(($G$2:$G$300)="outbound"))>0,"outbound", IF(SUMPRODUCT((LEN(B152)-LEN(SUBSTITUTE(B152,$F$2:$F$300,"")))*(($G$2:$G$300)="inbound"))>0,"inbound","unknown")), "unknown" )} -> inbound | D152: =VLOOKUP(C152,$I$2:$J$5,2,FALSE) -> Block
A153: 47.238.121.28 | B153: "Exploit", "Scanner" | C153: {=IFERROR( IF(SUMPRODUCT((LEN(B153)-LEN(SUBSTITUTE(B153,$F$2:$F$300,"")))*(($G$2:$G$300)="outbound"))>0,"outbound", IF(SUMPRODUCT((LEN(B153)-LEN(SUBSTITUTE(B153,$F$2:$F$300,"")))*(($G$2:$G$300)="inbound"))>0,"inbound","unknown")), "unknown" )} -> inbound | D153: =VLOOKUP(C153,$I$2:$J$5,2,FALSE) -> Block
A154: 165.154.42.180 | B154: "Exploit", "Scanner" | C154: {=IFERROR( IF(SUMPRODUCT((LEN(B154)-LEN(SUBSTITUTE(B154,$F$2:$F$300,"")))*(($G$2:$G$300)="outbound"))>0,"outbound", IF(SUMPRODUCT((LEN(B154)-LEN(SUBSTITUTE(B154,$F$2:$F$300,"")))*(($G$2:$G$300)="inbound"))>0,"inbound","unknown")), "unknown" )} -> inbound | D154: =VLOOKUP(C154,$I$2:$J$5,2,FALSE) -> Block
A155: 152.32.186.194 | B155: "Exploit", "Scanner" | C155: {=IFERROR( IF(SUMPRODUCT((LEN(B155)-LEN(SUBSTITUTE(B155,$F$2:$F$300,"")))*(($G$2:$G$300)="outbound"))>0,"outbound", IF(SUMPRODUCT((LEN(B155)-LEN(SUBSTITUTE(B155,$F$2:$F$300,"")))*(($G$2:$G$300)="inbound"))>0,"inbound","unknown")), "unknown" )} -> inbound | D155: =VLOOKUP(C155,$I$2:$J$5,2,FALSE) -> Block
A156: 152.32.192.176 | B156: "Exploit", "BruteForcer", "Scanner" | C156: {=IFERROR( IF(SUMPRODUCT((LEN(B156)-LEN(SUBSTITUTE(B156,$F$2:$F$300,"")))*(($G$2:$G$300)="outbound"))>0,"outbound", IF(SUMPRODUCT((LEN(B156)-LEN(SUBSTITUTE(B156,$F$2:$F$300,"")))*(($G$2:$G$300)="inbound"))>0,"inbound","unknown")), "unknown" )} -> inbound | D156: =VLOOKUP(C156,$I$2:$J$5,2,FALSE) -> Block
A157: 36.255.223.90 | B157: "Exploit", "Scanner" | C157: {=IFERROR( IF(SUMPRODUCT((LEN(B157)-LEN(SUBSTITUTE(B157,$F$2:$F$300,"")))*(($G$2:$G$300)="outbound"))>0,"outbound", IF(SUMPRODUCT((LEN(B157)-LEN(SUBSTITUTE(B157,$F$2:$F$300,"")))*(($G$2:$G$300)="inbound"))>0,"inbound","unknown")), "unknown" )} -> inbound | D157: =VLOOKUP(C157,$I$2:$J$5,2,FALSE) -> Block
A158: 58.152.25.253 | B158: "Exploit", "BruteForcer", "Scanner" | C158: {=IFERROR( IF(SUMPRODUCT((LEN(B158)-LEN(SUBSTITUTE(B158,$F$2:$F$300,"")))*(($G$2:$G$300)="outbound"))>0,"outbound", IF(SUMPRODUCT((LEN(B158)-LEN(SUBSTITUTE(B158,$F$2:$F$300,"")))*(($G$2:$G$300)="inbound"))>0,"inbound","unknown")), "unknown" )} -> inbound | D158: =VLOOKUP(C158,$I$2:$J$5,2,FALSE) -> Block
... A1180: 158.247.210.58 | B1180: "APT43" | C1180: {=IFERROR( IF(SUMPRODUCT((LEN(B1180)-LEN(SUBSTITUTE(B1180,$F$2:$F$300,"")))*(($G$2:$G$300)="outbound"))>0,"outbound", IF(SUMPRODUCT((LEN(B1180)-LEN(SUBSTITUTE(B1180,$F$2:$F$300,"")))*(($G$2:$G$300)="inbound"))>0,"inbound","unknown")), "unknown" )} -> unknown | D1180: =VLOOKUP(C1180,$I$2:$J$5,2,FALSE) -> Alert
A1181: archibase.co | C1181: {=IFERROR( IF(SUMPRODUCT((LEN(B1181)-LEN(SUBSTITUTE(B1181,$F$2:$F$300,"")))*(($G$2:$G$300)="outbound"))>0,"outbound", IF(SUMPRODUCT((LEN(B1181)-LEN(SUBSTITUTE(B1181,$F$2:$F$300,"")))*(($G$2:$G$300)="inbound"))>0,"inbound","unknown")), "unknown" )} -> unknown | D1181: =VLOOKUP(C1181,$I$2:$J$5,2,FALSE) -> Alert
A1182: cardcpp.online | B1182: "MiningDropper" | C1182: {=IFERROR( IF(SUMPRODUCT((LEN(B1182)-LEN(SUBSTITUTE(B1182,$F$2:$F$300,"")))*(($G$2:$G$300)="outbound"))>0,"outbound", IF(SUMPRODUCT((LEN(B1182)-LEN(SUBSTITUTE(B1182,$F$2:$F$300,"")))*(($G$2:$G$300)="inbound"))>0,"inbound","unknown")), "unknown" )} -> unknown | D1182: =VLOOKUP(C1182,$I$2:$J$5,2,FALSE) -> Alert
A1183: whereisitat.lucyatemysuperbox.space | B1183: "Xinference", "supply chain attack" | C1183: {=IFERROR( IF(SUMPRODUCT((LEN(B1183)-LEN(SUBSTITUTE(B1183,$F$2:$F$300,"")))*(($G$2:$G$300)="outbound"))>0,"outbound", IF(SUMPRODUCT((LEN(B1183)-LEN(SUBSTITUTE(B1183,$F$2:$F$300,"")))*(($G$2:$G$300)="inbound"))>0,"inbound","unknown")), "unknown" )} -> unknown | D1183: =VLOOKUP(C1183,$I$2:$J$5,2,FALSE) -> Alert
A1184: 151.245.195.142 | B1184: "ClickFix", "cmdkey", "lolbins" | C1184: {=IFERROR( IF(SUMPRODUCT((LEN(B1184)-LEN(SUBSTITUTE(B1184,$F$2:$F$300,"")))*(($G$2:$G$300)="outbound"))>0,"outbound", IF(SUMPRODUCT((LEN(B1184)-LEN(SUBSTITUTE(B1184,$F$2:$F$300,"")))*(($G$2:$G$300)="inbound"))>0,"inbound","unknown")), "unknown" )} -> inbound | D1184: =VLOOKUP(C1184,$I$2:$J$5,2,FALSE) -> Block
A1185: nuevaprodeciencia.club | B1185: "agenteV2", "banking trojan" | C1185: {=IFERROR( IF(SUMPRODUCT((LEN(B1185)-LEN(SUBSTITUTE(B1185,$F$2:$F$300,"")))*(($G$2:$G$300)="outbound"))>0,"outbound", IF(SUMPRODUCT((LEN(B1185)-LEN(SUBSTITUTE(B1185,$F$2:$F$300,"")))*(($G$2:$G$300)="inbound"))>0,"inbound","unknown")), "unknown" )} -> unknown | D1185: =VLOOKUP(C1185,$I$2:$J$5,2,FALSE) -> Alert
A1186: 46.37.123.101 | B1186: "PhantomCore", "KermitRAT" | C1186: {=IFERROR( IF(SUMPRODUCT((LEN(B1186)-LEN(SUBSTITUTE(B1186,$F$2:$F$300,"")))*(($G$2:$G$300)="outbound"))>0,"outbound", IF(SUMPRODUCT((LEN(B1186)-LEN(SUBSTITUTE(B1186,$F$2:$F$300,"")))*(($G$2:$G$300)="inbound"))>0,"inbound","unknown")), "unknown" )} -> unknown | D1186: =VLOOKUP(C1186,$I$2:$J$5,2,FALSE) -> Alert
A1187: 2.59.153.146 | B1187: "Scanner" | C1187: {=IFERROR( IF(SUMPRODUCT((LEN(B1187)-LEN(SUBSTITUTE(B1187,$F$2:$F$300,"")))*(($G$2:$G$300)="outbound"))>0,"outbound", IF(SUMPRODUCT((LEN(B1187)-LEN(SUBSTITUTE(B1187,$F$2:$F$300,"")))*(($G$2:$G$300)="inbound"))>0,"inbound","unknown")), "unknown" )} -> inbound | D1187: =VLOOKUP(C1187,$I$2:$J$5,2,FALSE) -> Block
A1188: 2.59.153.95 | B1188: "Scanner" | C1188: {=IFERROR( IF(SUMPRODUCT((LEN(B1188)-LEN(SUBSTITUTE(B1188,$F$2:$F$300,"")))*(($G$2:$G$300)="outbound"))>0,"outbound", IF(SUMPRODUCT((LEN(B1188)-LEN(SUBSTITUTE(B1188,$F$2:$F$300,"")))*(($G$2:$G$300)="inbound"))>0,"inbound","unknown")), "unknown" )} -> inbound | D1188: =VLOOKUP(C1188,$I$2:$J$5,2,FALSE) -> Block
A1189: 2.59.153.210 | B1189: "Scanner" | C1189: {=IFERROR( IF(SUMPRODUCT((LEN(B1189)-LEN(SUBSTITUTE(B1189,$F$2:$F$300,"")))*(($G$2:$G$300)="outbound"))>0,"outbound", IF(SUMPRODUCT((LEN(B1189)-LEN(SUBSTITUTE(B1189,$F$2:$F$300,"")))*(($G$2:$G$300)="inbound"))>0,"inbound","unknown")), "unknown" )} -> inbound | D1189: =VLOOKUP(C1189,$I$2:$J$5,2,FALSE) -> Block
A1190: 2.59.153.240 | B1190: "Scanner" | C1190: {=IFERROR( IF(SUMPRODUCT((LEN(B1190)-LEN(SUBSTITUTE(B1190,$F$2:$F$300,"")))*(($G$2:$G$300)="outbound"))>0,"outbound", IF(SUMPRODUCT((LEN(B1190)-LEN(SUBSTITUTE(B1190,$F$2:$F$300,"")))*(($G$2:$G$300)="inbound"))>0,"inbound","unknown")), "unknown" )} -> inbound | D1190: =VLOOKUP(C1190,$I$2:$J$5,2,FALSE) -> Block
A1191: 2.59.153.117 | B1191: "Scanner" | C1191: {=IFERROR( IF(SUMPRODUCT((LEN(B1191)-LEN(SUBSTITUTE(B1191,$F$2:$F$300,"")))*(($G$2:$G$300)="outbound"))>0,"outbound", IF(SUMPRODUCT((LEN(B1191)-LEN(SUBSTITUTE(B1191,$F$2:$F$300,"")))*(($G$2:$G$300)="inbound"))>0,"inbound","unknown")), "unknown" )} -> inbound | D1191: =VLOOKUP(C1191,$I$2:$J$5,2,FALSE) -> Block
A1192: 2.59.153.135 | B1192: "Scanner" | C1192: {=IFERROR( IF(SUMPRODUCT((LEN(B1192)-LEN(SUBSTITUTE(B1192,$F$2:$F$300,"")))*(($G$2:$G$300)="outbound"))>0,"outbound", IF(SUMPRODUCT((LEN(B1192)-LEN(SUBSTITUTE(B1192,$F$2:$F$300,"")))*(($G$2:$G$300)="inbound"))>0,"inbound","unknown")), "unknown" )} -> inbound | D1192: =VLOOKUP(C1192,$I$2:$J$5,2,FALSE) -> Block
A1193: 2.59.153.45 | B1193: "Scanner" | C1193: {=IFERROR( IF(SUMPRODUCT((LEN(B1193)-LEN(SUBSTITUTE(B1193,$F$2:$F$300,"")))*(($G$2:$G$300)="outbound"))>0,"outbound", IF(SUMPRODUCT((LEN(B1193)-LEN(SUBSTITUTE(B1193,$F$2:$F$300,"")))*(($G$2:$G$300)="inbound"))>0,"inbound","unknown")), "unknown" )} -> inbound | D1193: =VLOOKUP(C1193,$I$2:$J$5,2,FALSE) -> Block
... A10572: 115.186.175.29 | B10572: DDoS | C10572: {=IFERROR( IF(SUMPRODUCT((LEN(B10572)-LEN(SUBSTITUTE(B10572,$F$2:$F$300,"")))*(($G$2:$G$300)="outbound"))>0,"outbound", IF(SUMPRODUCT((LEN(B10572)-LEN(SUBSTITUTE(B10572,$F$2:$F$300,"")))*(($G$2:$G$300)="inbound"))>0,"inbound","unknown")), "unknown" )} -> inbound | D10572: =VLOOKUP(C10572,$I$2:$J$5,2,FALSE) -> Block
A10573: 123.59.186.141 | B10573: DDoS | C10573: Direction Mismatch: Outbound/Inbound Conflict | D10573: =VLOOKUP(C10573,$I$2:$J$5,2,FALSE) -> Alert
A10574: 136.124.34.65 | B10574: DDoS | C10574: {=IFERROR( IF(SUMPRODUCT((LEN(B10574)-LEN(SUBSTITUTE(B10574,$F$2:$F$300,"")))*(($G$2:$G$300)="outbound"))>0,"outbound", IF(SUMPRODUCT((LEN(B10574)-LEN(SUBSTITUTE(B10574,$F$2:$F$300,"")))*(($G$2:$G$300)="inbound"))>0,"inbound","unknown")), "unknown" )} -> inbound | D10574: =VLOOKUP(C10574,$I$2:$J$5,2,FALSE) -> Block
A10575: 115.186.175.16 | B10575: DDoS | C10575: {=IFERROR( IF(SUMPRODUCT((LEN(B10575)-LEN(SUBSTITUTE(B10575,$F$2:$F$300,"")))*(($G$2:$G$300)="outbound"))>0,"outbound", IF(SUMPRODUCT((LEN(B10575)-LEN(SUBSTITUTE(B10575,$F$2:$F$300,"")))*(($G$2:$G$300)="inbound"))>0,"inbound","unknown")), "unknown" )} -> inbound | D10575: =VLOOKUP(C10575,$I$2:$J$5,2,FALSE) -> Block
A10576: 115.186.175.17 | B10576: DDoS | C10576: {=IFERROR( IF(SUMPRODUCT((LEN(B10576)-LEN(SUBSTITUTE(B10576,$F$2:$F$300,"")))*(($G$2:$G$300)="outbound"))>0,"outbound", IF(SUMPRODUCT((LEN(B10576)-LEN(SUBSTITUTE(B10576,$F$2:$F$300,"")))*(($G$2:$G$300)="inbound"))>0,"inbound","unknown")), "unknown" )} -> inbound | D10576: =VLOOKUP(C10576,$I$2:$J$5,2,FALSE) -> Block
A10577: 115.186.175.21 | B10577: DDoS | C10577: {=IFERROR( IF(SUMPRODUCT((LEN(B10577)-LEN(SUBSTITUTE(B10577,$F$2:$F$300,"")))*(($G$2:$G$300)="outbound"))>0,"outbound", IF(SUMPRODUCT((LEN(B10577)-LEN(SUBSTITUTE(B10577,$F$2:$F$300,"")))*(($G$2:$G$300)="inbound"))>0,"inbound","unknown")), "unknown" )} -> inbound | D10577: =VLOOKUP(C10577,$I$2:$J$5,2,FALSE) -> Block
A10578: 115.186.175.22 | B10578: DDoS | C10578: {=IFERROR( IF(SUMPRODUCT((LEN(B10578)-LEN(SUBSTITUTE(B10578,$F$2:$F$300,"")))*(($G$2:$G$300)="outbound"))>0,"outbound", IF(SUMPRODUCT((LEN(B10578)-LEN(SUBSTITUTE(B10578,$F$2:$F$300,"")))*(($G$2:$G$300)="inbound"))>0,"inbound","unknown")), "unknown" )} -> inbound | D10578: =VLOOKUP(C10578,$I$2:$J$5,2,FALSE) -> Block
A10579: 115.186.175.26 | B10579: DDoS | C10579: {=IFERROR( IF(SUMPRODUCT((LEN(B10579)-LEN(SUBSTITUTE(B10579,$F$2:$F$300,"")))*(($G$2:$G$300)="outbound"))>0,"outbound", IF(SUMPRODUCT((LEN(B10579)-LEN(SUBSTITUTE(B10579,$F$2:$F$300,"")))*(($G$2:$G$300)="inbound"))>0,"inbound","unknown")), "unknown" )} -> inbound | D10579: =VLOOKUP(C10579,$I$2:$J$5,2,FALSE) -> Block
A10580: 115.186.175.27 | B10580: DDoS | C10580: {=IFERROR( IF(SUMPRODUCT((LEN(B10580)-LEN(SUBSTITUTE(B10580,$F$2:$F$300,"")))*(($G$2:$G$300)="outbound"))>0,"outbound", IF(SUMPRODUCT((LEN(B10580)-LEN(SUBSTITUTE(B10580,$F$2:$F$300,"")))*(($G$2:$G$300)="inbound"))>0,"inbound","unknown")), "unknown" )} -> inbound | D10580: =VLOOKUP(C10580,$I$2:$J$5,2,FALSE) -> Block
A10581: 203.184.192.192 | B10581: DDoS | C10581: {=IFERROR( IF(SUMPRODUCT((LEN(B10581)-LEN(SUBSTITUTE(B10581,$F$2:$F$300,"")))*(($G$2:$G$300)="outbound"))>0,"outbound", IF(SUMPRODUCT((LEN(B10581)-LEN(SUBSTITUTE(B10581,$F$2:$F$300,"")))*(($G$2:$G$300)="inbound"))>0,"inbound","unknown")), "unknown" )} -> inbound | D10581: =VLOOKUP(C10581,$I$2:$J$5,2,FALSE) -> Block
A10582: 218.255.186.134 | B10582: DDoS | C10582: {=IFERROR( IF(SUMPRODUCT((LEN(B10582)-LEN(SUBSTITUTE(B10582,$F$2:$F$300,"")))*(($G$2:$G$300)="outbound"))>0,"outbound", IF(SUMPRODUCT((LEN(B10582)-LEN(SUBSTITUTE(B10582,$F$2:$F$300,"")))*(($G$2:$G$300)="inbound"))>0,"inbound","unknown")), "unknown" )} -> inbound | D10582: =VLOOKUP(C10582,$I$2:$J$5,2,FALSE) -> Block
A10583: 58.215.234.8 | B10583: DDoS | C10583: {=IFERROR( IF(SUMPRODUCT((LEN(B10583)-LEN(SUBSTITUTE(B10583,$F$2:$F$300,"")))*(($G$2:$G$300)="outbound"))>0,"outbound", IF(SUMPRODUCT((LEN(B10583)-LEN(SUBSTITUTE(B10583,$F$2:$F$300,"")))*(($G$2:$G$300)="inbound"))>0,"inbound","unknown")), "unknown" )} -> inbound | D10583: =VLOOKUP(C10583,$I$2:$J$5,2,FALSE) -> Block
A10584: 117.231.192.83 | B10584: DDoS | C10584: {=IFERROR( IF(SUMPRODUCT((LEN(B10584)-LEN(SUBSTITUTE(B10584,$F$2:$F$300,"")))*(($G$2:$G$300)="outbound"))>0,"outbound", IF(SUMPRODUCT((LEN(B10584)-LEN(SUBSTITUTE(B10584,$F$2:$F$300,"")))*(($G$2:$G$300)="inbound"))>0,"inbound","unknown")), "unknown" )} -> inbound | D10584: =VLOOKUP(C10584,$I$2:$J$5,2,FALSE) -> Block
A10585: 172.59.184.210 | B10585: DDoS | C10585: {=IFERROR( IF(SUMPRODUCT((LEN(B10585)-LEN(SUBSTITUTE(B10585,$F$2:$F$300,"")))*(($G$2:$G$300)="outbound"))>0,"outbound", IF(SUMPRODUCT((LEN(B10585)-LEN(SUBSTITUTE(B10585,$F$2:$F$300,"")))*(($G$2:$G$300)="inbound"))>0,"inbound","unknown")), "unknown" )} -> inbound | D10585: =VLOOKUP(C10585,$I$2:$J$5,2,FALSE) -> Block
... A13001: hfvip.net/login | B13001: 金融機構 | C13001: {=IFERROR( IF(SUMPRODUCT((LEN(B13001)-LEN(SUBSTITUTE(B13001,$F$2:$F$300,"")))*(($G$2:$G$300)="outbound"))>0,"outbound", IF(SUMPRODUCT((LEN(B13001)-LEN(SUBSTITUTE(B13001,$F$2:$F$300,"")))*(($G$2:$G$300)="inbound"))>0,"inbound","unknown")), "unknown" )} -> unknown | D13001: =VLOOKUP(C13001,$I$2:$J$5,2,FALSE) -> Alert

Sheet Legend
A1: Label | B1: Traffic (Outbound/Inbound/Unknown) | D1: Classification | E1: Follow up action
A2: 釣魚網站 | B2: outbound | D2: Inbound | E2: Block
A3: Websafe.Phishing | B3: outbound | D3: Outbound | E3: Block
A4: Phishing | B4: outbound | D4: Unknown | E4: Alert
A5: Silver fox | B5: unknown | D5: Direction Mismatch: Outbound/Inbound Conflict | E5: Alert
A6: OceanLotus | B6: unknown
A7: Generic Trojan | B7: unknown
A8: BlackMarket | B8: unknown
A9: Gh0st | B9: unknown
A10: SilverFox | B10: unknown
A11: Botnet | B11: outbound
A12: CnC | B12: outbound
A13: Scanner | B13: inbound
A14: CyberAttack | B14: unknown
A15: Spam | B15: inbound
A16: BruteForcer | B16: inbound
A17: Asyncrat | B17: unknown
... A146: 無 | B146: unknown

Sheet -> HKCPSA Raw Files

Sheet 惡意事件(A)
A1: HKCSPA_CTIWG_威脅情報_惡意事件_通報TISC
A2: 序號 | B2: 事件類型 | C2: 攻擊源類型 | D2: 攻擊源 | E2: 攻擊源運營商信息 | F2: 攻擊源威脅分析 （數據來源於網絡公開數據，僅供參考） | G2: 數據標籤 | H2: 惡意文件樣本 （文件名與文件指紋，數據來源於網絡公開數據，僅供參考） | I2: 提交機構
A3: 1 | B3: APT攻擊 | C3: ip | D3: 103.40.79.139 | E3: TELEGLOBAL COMMUNICATION SERVICES LIMITED（香港ISP） | F3: 1.該IP存在6個惡意的C段IP 2.該IP地址使用了可疑證書，可能被用於通訊加密躲避檢測 3.該IP地址近期有爆破IOT-HIKCAM、端口掃描等行為 4.該IP存在被蜜罐捕獲的記錄 | G3: 無 | H3: 無 | I3: HKCSI
A4: 2 | B4: APT攻擊 | C4: ip | D4: 14.29.236.229 | E4: Kamatera, Inc.（全球性‌雲服務提供商‌） | F4: 1.該IP地址的通信樣本中，絕大部分是Starter惡意軟件。說明該IP地址與Starter惡意軟件關系密切 2.該IP的反查域名包含惡意域名：pool.ubuntu-search.online，pool.ubuntu-search.xyz 3.該IP存在23個惡意的C段IP 4.該IP地址使用了可疑證書，可能被用於通訊加密躲避檢測 5.該IP曾被海蓮花團夥組織用於惡意攻擊行為 | G4: APT組織：OceanLotus | H4: 無 | I4: HKCSI
A5: 3 | B5: APT攻擊 | C5: ip | D5: 103.57.248.171 | E5: EDIS GmbH（奧地利ISP） | F5: 1.該IP的反查域名包含惡意域名：avic-cn.org 2.該IP存在2個惡意的C段IP | G5: 無 | H5: 無 | I5: HKCSI
A6: 4 | B6: APT攻擊 | C6: ip | D6: 138.199.62.10 | E6: Datacamp Limited（英國IT設備及網絡服務服務商） | F6: 1.該IP有暴力破解、主機劫持、DDoS攻擊2.該IP包含僵屍網絡節點特征 3.該IP存在13個惡意的C段IP 4.該IP地址使用了可疑證書，可能被用於通訊加密躲避檢測 5.該IP近期發起過漏洞利用行為，利用包括Nortek Linear eMerge E3-Series設備命令注入攻擊(CVE-2022-31499)，OGNL表達式注入攻擊，Adobe ColdFusion AMF遠程代碼執行攻擊(CVE-2023-29300)等漏洞 6.該IP存在被蜜罐捕獲的記錄 | G6: 無 | H6: fef909da671e01bc870fde9da9cdcc46：Linux.Trojan.Dropper.Kajl | I6: HKCSI
A7: 5 | B7: APT攻擊 | C7: ip | D7: 118.99.2.23 | E7: 科盈電信集團有限公司 | F7: 1.該IP包含僵屍網絡節點特征 2.該IP存在1個惡意的C段IP 3.該IP近期發起過漏洞利用行為，利用包括YouPHPTube命令注入攻擊(CVE-2019-5127)，DedeCMS SQL注入攻擊(CVE-2017-17731)，OGNL表達式注入攻擊等漏洞 4.該IP存在被蜜罐捕獲的記錄 | G7: 無 | H7: 無 | I7: HKCSI
A8: 6 | B8: APT攻擊 | C8: ip | D8: 149.40.54.75 | E8: CDN77（英國CDN服務提供商） | F8: 1.該IP存在3個惡意的C段IP 2.該IP地址為動態IP，可能被黑客用作遠控服務器 3.該IP近期發起過漏洞利用行為，利用包括SQL注入攻擊，泛微e-cology遠程命令執行攻擊，泛微e-cology SQL注入攻擊等漏洞 4.該IP被蜜罐捕獲過，屬於非定向攻擊者，有廣泛的攻擊目標 | G8: 無 | H8: 無 | I8: HKCSI
A9: 7 | B9: APT攻擊 | C9: ip | D9: 185.225.234.192 | E9: TerraTransit AG（德國ISP） | F9: 1.該IP包含僵屍網絡節點特征 2.該IP存在50個惡意的C段IP 3.該IP近期發起過漏洞利用行為，利用包括SQL注入攻擊等漏洞 4.該IP存在被蜜罐捕獲的記錄 | G9: 無 | H9: 無 | I9: HKCSI
A10: 8 | B10: APT攻擊 | C10: ip | D10: 185.225.234.62 | E10: TerraTransit AG（德國ISP） | F10: 1.包含僵屍網絡節點特征 2.該IP存在50個惡意的C段IP 3.該IP近期發起過漏洞利用行為包括用友NC bsh-servlet-BshServlet遠程命令執行攻擊，web-xml文件讀取攻擊，藍淩OA文件包含攻擊(CNVD-2021-28277)等 4.該IP存在被蜜罐捕獲的記錄 | G10: 無 | H10: 無 | I10: HKCSI
A11: 9 | B11: APT攻擊 | C11: ip | D11: 156.146.45.194 | E11: Datacamp Limited（英國IT設備及網絡服務服務商） | F11: 1.該IP存在25個惡意的C段IP 2.該IP近期發起過漏洞利用行為，利用包括ThinkPHP SQL注入攻擊，Web權限繞過攻擊，SQL注入攻擊等漏洞 3.該IP存在被蜜罐捕獲的記錄 | G11: 無 | H11: 無 | I11: HKCSI
A12: 10 | B12: APT攻擊 | C12: ip | D12: 185.225.234.144 | E12: TerraTransit AG（德國ISP） | F12: 1.該IP包含僵屍網絡節點特征 2.該IP存在49個惡意的C段IP 3.該IP近期發起過漏洞利用行為，包括遠程命令執行，Cockpit CMS NoSQL注入攻擊(CVE-2020-35846)，Apache拒絕服務攻擊(CVE-2012-3526)等漏洞 5.該IP存在被蜜罐捕獲的記錄 | G12: 無 | H12: 無 | I12: HKCSI
A13: 11 | B13: APT攻擊 | C13: ip | D13: 38.180.150.40 | E13: 3NT SOLUTIONS LLP（英國VPS服務商） | F13: 1.該IP地址使用了可疑證書，可能被用於通訊加密躲避檢測 | G13: APT組織：OceanLotus | H13: 無 | I13: HKCSI
A14: 12 | B14: APT攻擊 | C14: ip | D14: 183.87.124.189 | E14: 華為（香港公有雲服務商） | F14: 1.該IP存在11個惡意的C段IP 2.該IP地址為動態IP，可能被黑客用作遠控服務器 3.該IP地址近期有對外的端口掃描行為 4.該IP存在被蜜罐捕獲的記錄 | G14: 無 | H14: 無 | I14: HKCSI
... A24: 22 | B24: 僵屍木馬 | C24: ip | D24: 143.92.51.10 | E24: RACKIP CONSULTANCY PTE. LTD.（香港BGP線路運營商） | F24: 1.該IP存在255個惡意的C段IP | G24: 無 | H24: 03c3f5c2f6e50060057b0404da558610：Win32.Trojan.Cyclun.Fajl | I24: HKCSI
A25: 23 | B25: 僵屍木馬 | C25: ip | D25: 17.253.87.196 | E25: 蘋果公司 | F25: 1.該IP包含僵屍網絡節點特征 2.該IP地址有Apple Inc.頒發的有效證書，頒發給Apple Inc. 3.該IP地址近期有對外的端口掃描行為 | G25: 無 | I25: HKCSI
A26: 24 | B26: 僵屍木馬 | C26: ip | D26: 23.2.16.48 | E26: 阿卡邁（美國CDN服務提供商） | F26: 1.該IP存在1個惡意的C段IP 3.該IP地址近期有對外的端口掃描行為 4.該IP存在被蜜罐捕獲的記錄 | G26: 無 | H26: bc8984fefdb3931c214037ebc5a94d9a：Win32.Trojan.Inject.Sgil 368faf3e565f4c7f398225e719991226：Win32.Trojan.Jorik.Vimw 33c6b605e975a2910ce9c3cdd822f7f4：Win32.Trojan.Jorik.Ssmw c986342af7319980d32b10cd78e952c5：Win32.Trojan.Jorik.Twhl 9748acf159711317ce5cd85f39eb393b：Win32.Trojan.Jorik.Jcnw 等16個樣本 | I26: HKCSI
A27: 25 | B27: 僵屍木馬 | C27: ip | D27: 23.33.92.22 | E27: 阿卡邁（美國CDN服務提供商） | F27: 1.該IP包含僵屍網絡節點特征 2.該IP存在1個惡意的C段IP 3.該IP地址使用了可疑證書，可能被用於通訊加密躲避檢測 4.該IP地址近期有對外的端口掃描行為 5.該IP存在被蜜罐捕獲的記錄 | G27: 無 | H27: 4c8bd02ee339eb24aed1ce55d5ff85dc：Win32.AdWare.Adload.Xwhl acc889e3b0e8390270d9bf12de25e1dd：Win32.AdWare.Adload.Dzlw f7366551864aabd59673a06bfe4fcaa8：Win32.AdWare.Adload.Icnw b030baa32259d14910fd03c8803f877a：Win32.AdWare.Adload.Zfow 2d3845e0fd3bf86308d1b5148db59cf8：Win32.AdWare.Adload.Ddhl 等6個樣本 | I27: HKCSI
A28: 26 | B28: 僵屍木馬 | C28: ip | D28: 27.124.2.150 | E28: RACKIP CONSULTANCY PTE. LTD.（香港BGP線路運營商） | F28: 1.該IP地址與Suschil、Kryptik_AGen、Generic等惡意軟件有通信行為 2.該IP存在252個惡意的C段IP | G28: 惡意文件家族：Generic Trojan | H28: 39a5d58a2c55a97e784fb1caa14e35ec：Win32.Trojan.FalseSign.Hajl 917f01536b3ecf7205fc7bee39df9004：Win32.Trojan.Silverfox.Wmhl 5c5700ece4c6450f39204a183e5b51b3：Win32.Trojan.Silverfox.Vmhl 0ac9f2b4e20576608fa2908c589738a8：Win32.Trojan.Silverfox.Oqil 74ff5bc33f50041e702618b44a83468f：Win32.Trojan.Silverfox.Jqil 等8個樣本 | I28: HKCSI
A29: 27 | B29: 僵屍木馬 | C29: ip | D29: 43.152.24.67 | E29: 騰訊（香港公有雲服務商） | F29: 1.該IP有DDoS攻擊.該IP存在13個惡意的C段IP 3.該IP地址為動態IP，可能被黑客用作遠控服務器 4.該IP地址近期有對外的端口掃描行為 | G29: 無 | H29: 9d1d65b002c9f47e2628315b75f55bc9：Win32.Backdoor.Agent.Rsmw 77e4cdffc7bc3f27d91c5c624231f16f：Win32.Trojan.Generic.Cnhl 3a2a07fb9d15d68d6b294479fd581256：Win32.Trojan.Silverfox.Qgil 9230d634802feb96608cc1d31ce7512c：Win32.Trojan.Generic.Yolw 375e61f7d7919121ac906b1f6301ae5c：Win32.Trojan.Generic.Qsmw 等52個樣本 | I29: HKCSI
A30: 28 | B30: 僵屍木馬 | C30: ip | D30: 47.86.111.52 | E30: 阿裏雲（香港公有雲服務商） | F30: 1.該IP地址與灰色軟件LetsVPN等有通信行為，可能為灰產相關的IP地址 2.該IP的反查域名包含惡意域名：msthiyun.com，wentianskw168.com，wendalong168.com等 3.該IP地址使用了可疑證書，可能被用於通訊加密躲避檢測 | G30: 無 | H30: 2ae6454dcb7da2278b7330f5cd63f3ba：Win64.Backdoor.Phish-e.Ogil ee4106b808af37ef3381d035d4faeb7b：Win64.Backdoor.Phish-e.Gflw 92a7ece9cb406d15c3139fe1d181b0e2：Win32.Backdoor.Phish-e.Rsmw aa3311f399b7a10f1e3abd6fe0fc512c：Win32.Backdoor.Phish-e.Qsmw c777ae3fff97e19f483caffe806c8add：Win32.Backdoor.Phish-e.Kmnw 等54個樣本 | I30: HKCSI
A31: 29 | B31: 殭屍網絡感染 | C31: ip | D31: 149.104.0.145 | E31: XNNET LLC | G31: "BlackMarket", "Gh0st", "SilverFox", "Botnet" | I31: SSWK
A32: 30 | B32: 其他惡意事件 | C32: ip | D32: 192.238.180.148 | E32: Antbox Networks Limited | G32: "SilverFox", "CnC" | I32: SSWK
A33: 31 | B33: 其他惡意事件 | C33: ip | D33: 38.181.2.20 | E33: Hong Kong Communications International Co., Limited | G33: "SilverFox", "CnC" | I33: SSWK
A34: 32 | B34: 常規網絡攻擊 | C34: ip | D34: 143.92.32.165 | E34: CTG Server Limited | G34: "Scanner", "CyberAttack", "Spam", "Botnet", "BruteForcer" | I34: SSWK
A35: 33 | B35: 其他惡意事件 | C35: ip | D35: 202.79.174.192 | E35: CTG Server Limited | G35: "SilverFox", "CnC" | I35: SSWK
A36: 34 | B36: 殭屍網絡感染 | C36: ip | D36: 27.124.4.107 | E36: CTG Server Limited | G36: "Gh0st", "SilverFox", "Botnet" | I36: SSWK
A37: 35 | B37: 木馬感染 | C37: ip | D37: 47.83.225.15 | E37: Alibaba Cloud | G37: "Asyncrat", "Malware" | I37: SSWK
A38: 36 | B38: 其他惡意事件 | C38: ip | D38: 45.119.98.105 | E38: SonderCloud Limited | G38: "CnC" | I38: SSWK
A39: 37 | B39: 木馬感染 | C39: ip | D39: 154.38.113.14 | E39: Hong Kong Communications International Co., Limited | G39: "Malware", "SilverFox", "GoldenEyeDog" | I39: SSWK
A40: 38 | B40: 其他惡意事件 | C40: ip | D40: 47.86.111.52 | E40: Alibaba Cloud | G40: "SilverFox", "CnC" | I40: SSWK
A41: 39 | B41: 木馬感染 | C41: ip | D41: 27.124.43.226 | E41: CTG Server Limited | G41: "Malware", "GoldenEyeDog" | I41: SSWK
A42: 40 | B42: 木馬感染 | C42: ip | D42: 206.233.240.116 | E42: Zillion Network Inc. | G42: "Malware" | I42: SSWK
... A184: 182 | B184: 常規網絡攻擊 | C184: ip | D184: 223.17.47.129 | E184: HGC Global Communications Limited | G184: "Exploit", "CyberAttack", "Scanner" | I184: SSWK

Sheet 涉港釣魚網站專報
A1: HKCSPA_CTIWG_威脅情報_涉港釣魚網站專報_通報TISC
A2: 序號 | B2: 釣魚網站數據類型 | C2: 釣魚網站數據 | D2: 數據標籤 | E2: 提交機構
A3: 1 | B3: domain | C3: heeso.cis-edu.hk | D3: "釣魚網站", "Websafe.Phishing" | E3: 360
A4: 2 | B4: domain | C4: 00371.hk | D4: "釣魚網站", "Websafe.Phishing" | E4: 360
A5: 3 | B5: domain | C5: 2021.hk | D5: "釣魚網站", "Phishing" | E5: 360
A6: 4 | B6: domain | C6: 2021.hk | D6: "釣魚網站", "Phishing" | E6: 360
A7: 5 | B7: domain | C7: m3g3.hk | D7: "釣魚網站", "Websafe.Phishing" | E7: 360
A8: 6 | B8: domain | C8: zly.cis-edu.hk | D8: "釣魚網站", "Websafe.Phishing" | E8: 360
A9: 7 | B9: domain | C9: 798.hk | D9: "釣魚網站", "Websafe.Phishing" | E9: 360
A10: 8 | B10: domain | C10: pyd.cis-edu.hk | D10: "釣魚網站", "Websafe.Phishing" | E10: 360
A11: 9 | B11: domain | C11: 6uco6wrg.00489.hk | D11: "釣魚網站", "Websafe.Phishing" | E11: 360
A12: 10 | B12: domain | C12: aiqrta01.09626.hk | D12: "釣魚網站", "Websafe.Phishing" | E12: 360
A13: 11 | B13: domain | C13: ng.02328.hk | D13: "釣魚網站", "Websafe.Phishing" | E13: 360
A14: 12 | B14: domain | C14: vhy.hk | D14: "釣魚網站", "Websafe.Phishing" | E14: 360
... A402: 400 | B402: domain | C402: tdkf37.ime.hk | D402: "釣魚網站", "Silver fox" | E402: 360
B403: 數據支撐機構：360
B404: 數據整編機構：CTIWG技術支持團隊（香港網絡安全研究院）
B405: 數據問題溝通：ctiwg@hkcsi.hk

Sheet 惡意事件(B)
A1: HKCSPA_CTIWG_威脅情報_惡意事件_通報會員機構
A2: 序號 | B2: 事件類型 | C2: 攻擊源類型 | D2: 攻擊源 | E2: 攻擊源運營商 | F2: 攻擊目標類型 | G2: 攻擊目標 | H2: 攻擊目標運營商 | I2: 數據標籤 | J2: 提交機構
A3: 1 | B3: 掃描探測 | C3: ip | D3: 209.54.101.94 | I3: 掃描操作 | J3: HKCSI
A4: 2 | B4: 掃描探測 | C4: ip | D4: 213.209.159.233 | I4: TCP連接 | J4: HKCSI
A5: 3 | B5: 掃描探測 | C5: ip | D5: 45.148.10.49 | I5: TCP連接 | J5: HKCSI
A6: 4 | B6: 掃描探測 | C6: ip | D6: 209.38.240.240 | I6: 掃描操作 | J6: HKCSI
A7: 5 | B7: 掃描探測 | C7: ip | D7: 213.209.159.232 | I7: TCP連接 | J7: HKCSI
A8: 6 | B8: 掃描探測 | C8: ip | D8: 45.148.10.47 | I8: TCP連接 | J8: HKCSI
A9: 7 | B9: 掃描探測 | C9: ip | D9: 45.148.10.63 | I9: TCP連接 | J9: HKCSI
A10: 8 | B10: 掃描探測 | C10: ip | D10: 45.148.10.48 | I10: TCP連接 | J10: HKCSI
A11: 9 | B11: 掃描探測 | C11: ip | D11: 45.148.10.87 | I11: TCP連接 | J11: HKCSI
A12: 10 | B12: 掃描探測 | C12: ip | D12: 198.23.194.254 | I12: 掃描操作 | J12: HKCSI
A13: 11 | B13: 掃描探測 | C13: ip | D13: 154.23.238.16 | I13: 掃描操作 | J13: HKCSI
A14: 12 | B14: 掃描探測 | C14: ip | D14: 154.23.238.17 | I14: 掃描操作 | J14: HKCSI
... A535: 533 | B535: 掃描探測 | C535: ip | D535: 140.245.36.218 | I535: TCP轉發,TCP連接,HTTP訪問 | J535: HKCSI
A536: 534 | B536: 病毒感染 | C536: domain | D536: aomais.com | E536: The Constant Company, LLC | F536: ip | G536: 103.117.72.240 | H536: Zhengxing Technology | I536: "蠕蟲", "Pykspa" | J536: 360
A537: 535 | B537: 木馬感染 | C537: domain | D537: cwyfknmwh.biz | E537: SoftLayer Technologies Inc. | F537: ip | G537: 43.132.184.239 | H537: 騰訊 | I537: "木馬", "M0yv" | J537: 360
A538: 536 | B538: 木馬感染 | C538: domain | D538: unassigned.calpop.com | E538: GoDaddy.com, LLC | F538: ip | G538: 154.12.31.87 | H538: cognetcloud INC | I538: "木馬", "Trojangen" | J538: 360
A539: 537 | B539: 木馬感染 | C539: domain | D539: apple.vzboot.com | E539: Private Layer INC | F539: ip | G539: 103.73.160.198 | H539: cognetcloud INC | I539: "木馬", "Reconyc" | J539: 360
A540: 538 | B540: 木馬感染 | C540: domain | D540: o.0ye.pw | E540: 騰訊 | F540: ip | G540: 103.96.72.126 | H540: Cloudie Limited | I540: "木馬", "Generic" | J540: 360
A541: 539 | B541: 木馬感染 | C541: domain | D541: a.xulehe.abrdns.com | E541: PEG TECH INC | F541: ip | G541: 43.246.210.69 | H541: Hong Kong San Ai Net Int'l Limited | I541: "木馬", "Farfli" | J541: 360
A542: 540 | B542: 木馬感染 | C542: domain | D542: ai.microsoftgpt.net | E542: 阿裏雲 | F542: ip | G542: 203.12.200.250 | H542: 中國電信 | I542: "木馬", "Trojangen" | J542: 360
A543: 541 | B543: 木馬感染 | C543: domain | D543: bs.lastcode.xyz | E543: SonderCloud Limited | F543: ip | G543: 103.112.96.88 | H543: AROSSCLOUD INC. | I543: "木馬", "Rekoobe" | J543: 360
A544: 542 | B544: 木馬感染 | C544: domain | D544: viacolor.ind.br | E544: Skymail Serviços de Computação e Provimento de Inf | F544: ip | G544: 47.75.171.70 | H544: 阿裏雲 | I544: "木馬", "Trojangen" | J544: 360
A545: 543 | B545: 木馬感染 | C545: domain | D545: a.xulehe.abrdns.com | E545: PEG TECH INC | F545: ip | G545: 123.58.218.193 | H545: 優刻得信息科技（香港）有限公司 | I545: "木馬", "Farfli" | J545: 360
A546: 544 | B546: 挖礦軟件感染 | C546: domain | D546: donate.ssl.xmrig.com | E546: DigitalOcean, LLC | F546: ip | G546: 103.112.185.132 | H546: Cloudie Limited | I546: "挖礦事件", "Miningpool" | J546: 360
A547: 545 | B547: 挖礦軟件感染 | C547: domain | D547: pool-fr.supportxmr.com | E547: OVH SAS | F547: ip | G547: 147.161.32.140 | H547: 戴訊互聯有限公司 | I547: "挖礦事件", "XMRig" | J547: 360
... A555: 553 | B555: 挖礦軟件感染 | C555: domain | D555: donate.ssl.xmrig.com | E555: DigitalOcean, LLC | F555: ip | G555: 154.201.85.209 | H555: cognetcloud INC | I555: "挖礦事件", "Miningpool" | J555: 360
A556: 554 | B556: 木馬感染 | C556: domain | D556: cacgp.despacito5.com | F556: ip | G556: 8.218.153.243 | H556: 阿裏雲 | I556: "木馬", "Generic" | J556: 360
A557: 555 | B557: 木馬感染 | C557: domain | D557: cacgp.despacito5.com | F557: ip | G557: 8.210.77.229 | H557: 阿裏雲 | I557: "木馬", "Generic" | J557: 360
A558: 556 | B558: 挖礦軟件感染 | C558: domain | D558: supportxmr.com | E558: 阿卡邁 | F558: ip | G558: 45.114.125.90 | H558: HanMing HK Limited | I558: "挖礦事件", "BitCoinMiner" | J558: 360
A559: 557 | B559: 木馬感染 | C559: domain | D559: s1-i47p.5588888.xyz | E559: OVH SAS | F559: ip | G559: 103.106.189.173 | H559: cognetcloud INC | I559: "木馬", "Generic" | J559: 360
A560: 558 | B560: 挖礦軟件感染 | C560: domain | D560: supportxmr.com | E560: 阿卡邁 | F560: ip | G560: 103.242.3.71 | H560: Cloudie Limited | I560: "挖礦事件", "BitCoinMiner" | J560: 360
A561: 559 | B561: 木馬感染 | C561: domain | D561: jhvzpcfg.biz | E561: 亞馬遜 | F561: ip | G561: 43.132.184.239 | H561: 騰訊 | I561: "木馬", "Zegost" | J561: 360
A562: 560 | B562: 挖礦軟件感染 | C562: domain | D562: pool.hashvault.pro | E562: HIVELOCITY, Inc. | F562: ip | G562: 154.201.85.209 | H562: cognetcloud INC | I562: "挖礦事件", "BitCoinMiner" | J562: 360
A563: 561 | B563: 木馬感染 | C563: domain | D563: ssl.aaaaaaaa.cyou | E563: FASTNET DATA INC | F563: ip | G563: 103.73.163.240 | H563: cognetcloud INC | I563: "木馬", "Generic" | J563: 360
A564: 562 | B564: 挖礦軟件感染 | C564: domain | D564: coopmobil.cz | E564: O2 Czech Republic, a.s. | F564: ip | G564: 103.118.195.217 | H564: Cloudie Limited | I564: "挖礦事件", "Miner_general" | J564: 360
A565: 563 | B565: 木馬感染 | C565: domain | D565: 1.192-168-0-1.top | E565: Ansheng Network Technology Co., Limited | F565: ip | G565: 43.154.107.230 | H565: 騰訊 | I565: "木馬", "Generic" | J565: 360
A566: 564 | B566: 木馬感染 | C566: domain | D566: Kew.8dfabcdef.us | E566: 阿裏雲 | F566: ip | G566: 103.149.201.111 | H566: cognetcloud INC | I566: "木馬", "Generic" | J566: 360
A567: 565 | B567: 木馬感染 | C567: domain | D567: Kew.8dfabcdef.us | E567: 阿裏雲 | F567: ip | G567: 103.255.45.144 | H567: 網時集團有限公司 | I567: "木馬", "Generic" | J567: 360
A568: 566 | B568: 挖礦軟件感染 | C568: domain | D568: btcssl-asia.f2pool.com | E568: Cloudflare, Inc. | F568: ip | G568: 128.1.132.42 | H568: 優刻得信息科技（香港）有限公司 | I568: "挖礦事件", "Public_miner_pool" | J568: 360
A569: 567 | B569: 木馬感染 | C569: domain | D569: drav31884.airdns.org | E569: Global Layer B.V. | F569: ip | G569: 45.114.125.90 | H569: HanMing HK Limited | I569: "木馬", "Generic" | J569: 360
... A575: 573 | B575: 木馬感染 | C575: domain | D575: tsh.akamaizes.com | E575: HostPapa | F575: ip | G575: 154.220.2.28 | H575: Gigabit Hosting Sdn Bhd | I575: "木馬", "Generic" | J575: 360
A576: 574 | B576: 木馬感染 | C576: ip | D576: 62.60.226.200 | I576: "Vidar", "C2", "go compiler", "staging", "telegram page" | J576: TRX
A577: 575 | B577: 常規網絡攻擊 | C577: domain | D577: gz.technicalprorj.xyz | I577: "multi-stage attack", "c2 communication" | J577: TRX
A578: 576 | B578: APT攻擊 | C578: domain | D578: 2zrek3mkl72d5b6evpkx2rz2glzrltiorgblpfb2ttg6lacwlsdk4iqd.onion | E578: APT-C-13 (Sandworm) | I578: "APT-C-13", "Sandworm" | J578: TRX
A579: 577 | B579: 木馬感染 | C579: domain | D579: onfinality.pro | I579: "GachiLoader", "Rhadamanthys", "blockchain c2" | J579: TRX
A580: 578 | B580: 木馬感染 | C580: ip | D580: 24.152.36.241 | I580: "LofyStealer", "Minecraft" | J580: TRX
A581: 579 | B581: 常規網絡攻擊 | C581: domain | D581: robinhuds.com | I581: "ClickFix", "HijackLoader" | J581: TRX
A582: 580 | B582: APT攻擊 | C582: domain | D582: 2zrek3mkl72d5b6evpkx2rz2glzrltiorgblpfb2ttg6lacwlsdk4iqd.onion | E582: APT-C-13 (Sandworm) | I582: "APT-C-13", "Sandworm" | J582: TRX
A583: 581 | B583: 常規網絡攻擊 | C583: domain | D583: api.kali365.xyz | I583: "OAuth abuse" | J583: TRX
A584: 582 | B584: 勒索軟件感染 | C584: domain | D584: kyblogtz6k3jtxnjjvluee5ec4g3zcnvyvbgsnq5thumphmqidkt7xid.onion | I584: "Kyber" | J584: TRX
A585: 583 | B585: 木馬感染 | C585: domain | D585: jsonapi.biz | I585: "KYCShadow", "Android banking trojan" | J585: TRX
A586: 584 | B586: 常規網絡攻擊 | C586: ip | D586: 65.111.25.67 | I586: "SQL injection" | J586: TRX
A587: 585 | B587: APT攻擊 | C587: ip | D587: 104.145.210.107 | E587: Lazarus | I587: "BlueNoroff", "Lazarus" | J587: TRX
A588: 586 | B588: 常規網絡攻擊 | C588: domain | D588: ftpbd.net | I588: "BlobPhish" | J588: TRX
A589: 587 | B589: 木馬感染 | C589: domain | D589: arkypc.com | I589: "AMOS Stealer" | J589: TRX
A590: 588 | B590: 常規網絡攻擊 | C590: ip | D590: 185.107.74.167 | I590: "phishing" | J590: TRX
A591: 589 | B591: 勒索軟件感染 | C591: ip | D591: 111.235.93.125 | E591: CL-CRI-1116 | I591: "BlackFile", "Cordial Spider" | J591: TRX
A592: 590 | B592: 後門軟件感染 | C592: domain | D592: login.collegefan.org | I592: "uWarrior", "ctOS RAT" | J592: TRX
A593: 591 | B593: APT攻擊 | C593: domain | D593: 1drv.one | E593: GLITTER CARP / SEQUIN CARP | I593: "GLITTER CARP", "SEQUIN CARP" | J593: TRX
A594: 592 | B594: 木馬感染 | C594: domain | D594: arkypc.com | I594: "AMOS Stealer" | J594: TRX
A595: 593 | B595: 常規網絡攻擊 | C595: ip | D595: 45.89.106.147 | I595: "malware analysis", "Adobe Reader" | J595: TRX
A596: 594 | B596: 木馬感染 | C596: domain | D596: chi.botick.top | I596: "Vidar", "infostealer", "credential theft" | J596: TRX
A597: 595 | B597: 常規網絡攻擊 | C597: domain | D597: audit.checkmarx.cx | E597: TeamPCP | I597: "npm", "supply chain" | J597: TRX
A598: 596 | B598: 常規網絡攻擊 | C598: domain | D598: air-upsuomi.fi | I598: "Fibergrid", "bulletproof hosting" | J598: TRX
A599: 597 | B599: APT攻擊 | C599: ip | D599: 158.247.210.58 | E599: Kimsuky | I599: "APT43" | J599: TRX
A600: 598 | B600: 常規網絡攻擊 | C600: domain | D600: archibase.co | J600: TRX
A601: 599 | B601: 木馬感染 | C601: domain | D601: cardcpp.online | I601: "MiningDropper" | J601: TRX
A602: 600 | B602: 常規網絡攻擊 | C602: domain | D602: whereisitat.lucyatemysuperbox.space | I602: "Xinference", "supply chain attack" | J602: TRX
A603: 601 | B603: 常規網絡攻擊 | C603: ip | D603: 151.245.195.142 | I603: "ClickFix", "cmdkey", "lolbins" | J603: TRX
A604: 602 | B604: 木馬感染 | C604: domain | D604: nuevaprodeciencia.club | I604: "agenteV2", "banking trojan" | J604: TRX
A605: 603 | B605: APT攻擊 | C605: ip | D605: 46.37.123.101 | E605: PhantomCore | I605: "PhantomCore", "KermitRAT" | J605: TRX
A606: 604 | B606: 其他惡意事件 | C606: ip | D606: 2.59.153.146 | E606: Hdtidc Limited | I606: "Scanner" | J606: SSWK
A607: 605 | B607: 其他惡意事件 | C607: ip | D607: 2.59.153.95 | E607: Hdtidc Limited | I607: "Scanner" | J607: SSWK
A608: 606 | B608: 其他惡意事件 | C608: ip | D608: 2.59.153.210 | E608: Hdtidc Limited | I608: "Scanner" | J608: SSWK
A609: 607 | B609: 其他惡意事件 | C609: ip | D609: 2.59.153.240 | E609: Hdtidc Limited | I609: "Scanner" | J609: SSWK
A610: 608 | B610: 其他惡意事件 | C610: ip | D610: 2.59.153.117 | E610: Hdtidc Limited | I610: "Scanner" | J610: SSWK
A611: 609 | B611: 其他惡意事件 | C611: ip | D611: 2.59.153.135 | E611: Hdtidc Limited | I611: "Scanner" | J611: SSWK
A612: 610 | B612: 其他惡意事件 | C612: ip | D612: 2.59.153.45 | E612: Hdtidc Limited | I612: "Scanner" | J612: SSWK
A613: 611 | B613: 其他惡意事件 | C613: ip | D613: 2.59.153.32 | E613: Hdtidc Limited | I613: "Scanner" | J613: SSWK
A614: 612 | B614: 其他惡意事件 | C614: ip | D614: 2.59.153.111 | E614: Hdtidc Limited | I614: "Scanner" | J614: SSWK
A615: 613 | B615: 其他惡意事件 | C615: ip | D615: 2.59.153.99 | E615: Hdtidc Limited | I615: "Scanner" | J615: SSWK
A616: 614 | B616: 其他惡意事件 | C616: ip | D616: 2.59.153.205 | E616: Hdtidc Limited | I616: "Scanner" | J616: SSWK
... A966: 964 | B966: 其他惡意事件 | C966: ip | D966: 103.183.193.156 | E966: Spectrum Cable network and broadband, Inc. | I966: "Exploit", "CyberAttack" | J966: SSWK
A967: 965 | B967: 其他惡意事件 | C967: ip | D967: 103.183.30.197 | I967: "Exploit", "CyberAttack" | J967: SSWK
A968: 966 | B968: 其他惡意事件 | C968: ip | D968: 103.183.62.2 | E968: Hasan Broadband Net | I968: "Exploit", "CyberAttack" | J968: SSWK
A969: 967 | B969: 其他惡意事件 | C969: ip | D969: 103.183.75.228 | E969: PT Cloud Hosting Indonesia | I969: "Exploit", "CyberAttack" | J969: SSWK
A970: 968 | B970: 其他惡意事件 | C970: ip | D970: 103.185.242.165 | E970: Digiana Speed Net Private Limited | I970: "Exploit", "CyberAttack" | J970: SSWK
A971: 969 | B971: 其他惡意事件 | C971: ip | D971: 103.185.53.93 | E971: PT DEWAWEB | I971: "Exploit", "CyberAttack" | J971: SSWK
A972: 970 | B972: 其他惡意事件 | C972: ip | D972: 103.186.0.19 | E972: PT Cloud Hosting Indonesia | I972: "Exploit", "CyberAttack" | J972: SSWK
A973: 971 | B973: 其他惡意事件 | C973: ip | D973: 103.186.1.103 | E973: PT Cloud Hosting Indonesia | I973: "Exploit", "CyberAttack" | J973: SSWK
A974: 972 | B974: 其他惡意事件 | C974: ip | D974: 103.186.1.150 | E974: PT Cloud Hosting Indonesia | I974: "Exploit", "CyberAttack" | J974: SSWK
A975: 973 | B975: 其他惡意事件 | C975: ip | D975: 103.186.151.77 | E975: Skylink Fibernet Private Limited | I975: "Exploit", "CyberAttack" | J975: SSWK
A976: 974 | B976: 其他惡意事件 | C976: ip | D976: 103.186.155.46 | E976: VIETPN Company Limited | I976: "Exploit", "CyberAttack" | J976: SSWK
A977: 975 | B977: 其他惡意事件 | C977: ip | D977: 103.186.49.225 | E977: Ekowebtech It Services Pvt Ltd | I977: "Exploit", "CyberAttack" | J977: SSWK
A978: 976 | B978: 其他惡意事件 | C978: ip | D978: 103.187.146.196 | E978: Cloud Host Pte Ltd | I978: "Exploit", "CyberAttack" | J978: SSWK
A979: 977 | B979: 其他惡意事件 | C979: ip | D979: 103.187.146.33 | E979: Cloud Host Pte Ltd | I979: "Exploit", "CyberAttack" | J979: SSWK
... A2184: 2182 | B2184: 其他惡意事件 | C2184: ip | D2184: 136.175.178.76 | E2184: DMIT Cloud Services | I2184: "Exploit", "CyberAttack" | J2184: SSWK
A2185: 2183 | B2185: 其他惡意事件 | C2185: ip | D2185: 136.175.83.27 | I2185: "Exploit", "CyberAttack" | J2185: SSWK
...

Sheet DDoS攻擊
A1: HKCSPA_CTIWG_威脅情報_DDoS攻擊員機構
A2: 序號 | B2: 攻擊源 | C2: 數據標籤 | D2: 提交機構
A3: 1 | B3: 43.248.102.16 | C3: TCPSYN | D3: HKCSI
A4: 2 | B4: 146.56.45.136 | C4: TCPSYN | D4: HKCSI
A5: 3 | B5: 121.170.41.10 | C5: TCPSYN | D5: HKCSI
A6: 4 | B6: 160.176.0.220 | C6: TCPSYN | D6: HKCSI
A7: 5 | B7: 70.70.43.123 | C7: TCPSYN | D7: HKCSI
A8: 6 | B8: 211.62.183.142 | C8: TCPSYN | D8: HKCSI
A9: 7 | B9: 111.180.200.247 | C9: TCPSYN | D9: HKCSI
A10: 8 | B10: 1.158.83.130 | C10: TCPSYN | D10: HKCSI
A11: 9 | B11: 70.171.204.72 | C11: TCPSYN | D11: HKCSI
A12: 10 | B12: 58.6.205.96 | C12: TCPSYN | D12: HKCSI
A13: 11 | B13: 20.125.40.198 | C13: TCPSYN | D13: HKCSI
A14: 12 | B14: 124.184.134.198 | C14: TCPSYN | D14: HKCSI
... A503: 501 | B503: 45.249.247.111 | C503: "Application DDoS攻擊E-2008-3263" | D503: SSWK
A504: 502 | B504: 141.98.83.48 | D504: HQQY
A505: 503 | B505: 192.81.211.118 | D505: HQQY
A506: 504 | B506: 144.91.107.104 | D506: HQQY
A507: 505 | B507: 1.34.42.95 | D507: HQQY
A508: 506 | B508: 205.166.28.150 | D508: HQQY
A509: 507 | B509: 39.170.42.35 | D509: HQQY
A510: 508 | B510: 169.233.63.7 | D510: HQQY
A511: 509 | B511: 140.224.74.123 | D511: HQQY
A512: 510 | B512: 115.186.175.13 | D512: HQQY
A513: 511 | B513: 165.225.246.34 | D513: HQQY
A514: 512 | B514: 115.186.175.28 | D514: HQQY
A515: 513 | B515: 103.239.20.130 | D515: HQQY
... A540: 538 | B540: 203.184.192.225 | D540: HQQY

Sheet 釣魚網站
A1: HKCSPA_CTIWG_威脅情報_釣魚網站_通報會員機構
A2: 序號 | B2: 釣魚網站數據類型 | C2: 釣魚網站數據 | D2: 數據標籤 | E2: 提交機構
A3: 1 | B3: ip | C3: 136.232.184.134 | E3: HKCSI
A4: 2 | B4: ip | C4: 78.188.106.53 | E4: HKCSI
A5: 3 | B5: ip | C5: 147.45.47.64 | E5: HKCSI
A6: 4 | B6: ip | C6: 38.110.228.43 | E6: HKCSI
A7: 5 | B7: ip | C7: 37.187.161.206 | E7: HKCSI
A8: 6 | B8: ip | C8: 110.24.36.35 | E8: HKCSI
A9: 7 | B9: ip | C9: 70.166.207.76 | E9: HKCSI
A10: 8 | B10: ip | C10: 31.31.77.83 | E10: HKCSI
A11: 9 | B11: ip | C11: 216.126.225.148 | E11: HKCSI
A12: 10 | B12: ip | C12: 146.70.137.90 | E12: HKCSI
A13: 11 | B13: ip | C13: 201.196.15.79 | E13: HKCSI
A14: 12 | B14: ip | C14: 18.228.7.109 | E14: HKCSI
... A319: 317 | B319: url | C319: https://tt.grupobedfs.com/.../gera_pdf.php | E319: HKCSI
A320: 318 | B320: url | C320: http://www.bet6663.cc/ | D320: "Phishing" | E320: SSWK
A321: 319 | B321: url | C321: https://bet98d.com/ | D321: "Phishing" | E321: SSWK
A322: 320 | B322: url | C322: https://www.paris-bet365.com.cn/ | D322: "Phishing" | E322: SSWK
A323: 321 | B323: url | C323: https://oily-bet365.com.cn/ | D323: "Phishing" | E323: SSWK
A324: 322 | B324: url | C324: https://www.head-bet365.com.cn/ | D324: "Phishing" | E324: SSWK
A325: 323 | B325: url | C325: https://www.choice-bet365.com.cn/ | D325: "Phishing" | E325: SSWK
A326: 324 | B326: url | C326: https://h5.metamaskvip.top/ | D326: "Phishing" | E326: SSWK
A327: 325 | B327: url | C327: https://www.crispy-bet365.com.cn/ | D327: "Phishing" | E327: SSWK
A328: 326 | B328: url | C328: https://k69g.top/ | D328: "Phishing" | E328: SSWK
A329: 327 | B329: url | C329: https://syszgd.com/ | D329: "Phishing" | E329: SSWK
A330: 328 | B330: url | C330: https://zh-coinbase.com/ | D330: "Phishing" | E330: SSWK
A331: 329 | B331: url | C331: http://www.jsylcz.com/ | D331: "Phishing" | E331: SSWK
... A1571: 1569 | B1571: url | C1571: https://appustart-ledgr.wixstudio.com/en-us | D1571: "Phishing" | E1571: SSWK
A1572: 1570 | B1572: domain | C1572: sorvaweithirau.pics | E1572: TRX
A1573: 1571 | B1573: domain | C1573: taskformulate.com | E1573: TRX
A1574: 1572 | B1574: domain | C1574: studcake.online | E1574: TRX
A1575: 1573 | B1575: domain | C1575: streamhoukend.info | E1575: TRX
A1576: 1574 | B1576: domain | C1576: tradei6-duac.com | E1576: TRX
A1577: 1575 | B1577: domain | C1577: syriandentalassociation.net | E1577: TRX
A1578: 1576 | B1578: domain | C1578: trenttubi.net | E1578: TRX
A1579: 1577 | B1579: domain | C1579: thesaloddrria.cfd | E1579: TRX
A1580: 1578 | B1580: domain | C1580: tokenizer360-app.com | E1580: TRX
A1581: 1579 | B1581: domain | C1581: thebreakingnowpulse.pro | E1581: TRX
A1582: 1580 | B1582: domain | C1582: tekgrupmedya.net | E1582: TRX
A1583: 1581 | B1583: domain | C1583: theuajondia.lol | E1583: TRX
... A2121: 2119 | B2121: domain | C2121: vivoospot.com | E2121: TRX
B2122: 數據支撐機構：HKCSI、SSWK、TRX
B2123: 數據整編機構：CTIWG技術支持團隊（香港網絡安全研究院）
B2124: 數據問題溝通：ctiwg@hkcsi.hk

Sheet 專題-全球風險IP通報
A1: HKCSPA_CTIWG_威脅情報_專題-全球風險IP通報_通報會員機構
A2: 序號 | B2: IOC類型 | C2: IOC | D2: IP歸屬國家 | E2: IP歸屬地區 | F2: 惡意類別 | G2: 惡意家族名稱 | H2: 提交機構
A3: 1 | B3: ip | C3: 13.248.169.48 | D3: 美國 | E3: - | F3: 僵屍網絡 | G3: Mirai | H3: HKCSI
A4: 2 | B4: ip | C4: 64.62.203.98 | D4: 美國 | E4: 聖莫尼卡 | F4: 僵屍網絡 | G4: vo1d | H4: HKCSI
A5: 3 | B5: ip | C5: 64.62.203.97 | D5: 美國 | E5: 聖莫尼卡 | F5: 僵屍網絡 | G5: vo1d | H5: HKCSI
A6: 4 | B6: ip | C6: 103.224.182.217 | D6: 美國 | E6: 聖地亞哥 | F6: 僵屍網絡 | G6: vo1d | H6: HKCSI
A7: 5 | B7: ip | C7: 96.7.244.133 | D7: 日本 | E7: 東京 | F7: 僵屍網絡 | G7: 僵屍網絡 | H7: HKCSI
A8: 6 | B8: ip | C8: 169.2.1.1 | D8: 美國 | E8: 薩克拉門托 | F8: 僵屍網絡 | G8: 僵屍網絡 | H8: HKCSI
A9: 7 | B9: ip | C9: 45.144.172.15 | D9: 荷蘭 | E9: 霍爾勒 | F9: 僵屍網絡 | G9: 僵屍網絡 | H9: HKCSI
A10: 8 | B10: ip | C10: 37.120.210.219 | D10: 日本 | E10: 東京 | F10: 僵屍網絡 | G10: 僵屍網絡 | H10: HKCSI
A11: 9 | B11: ip | C11: 213.152.161.30 | D11: 荷蘭 | E11: 阿姆斯特丹 | F11: 僵屍網絡 | G11: 僵屍網絡 | H11: HKCSI
A12: 10 | B12: ip | C12: 185.156.174.155 | D12: 捷克 | E12: 布拉格 | F12: 僵屍網絡 | G12: 僵屍網絡 | H12: HKCSI
A13: 11 | B13: ip | C13: 134.122.154.247 | D13: 日本 | E13: 東京 | F13: 僵屍網絡 | G13: 下載者 | H13: HKCSI
A14: 12 | B14: ip | C14: 185.156.175.35 | D14: 瑞士 | E14: 蘇黎世 | F14: 僵屍網絡 | G14: 僵屍網絡 | H14: HKCSI
... A82: 80 | B82: domain | C82: ee.bsjdwn.com | D82: - | E82: - | F82: 遠控木馬 | G82: - | H82: HKCSI
A83: 81 | B83: domain | C83: stigp.sa.com | D83: - | E83: - | F83: 遠控木馬 | G83: -
A84: 82 | B84: domain | C84: 3qq.qcommerceshop.com | D84: - | E84: - | F84: 竊密木馬 | G84: -
A85: 83 | B85: domain | C85: oone8de.cn | D85: - | E85: - | F85: 遠控木馬 | G85: -
A86: 84 | B86: domain | C86: lestvvkpn.com | D86: - | E86: - | F86: 遠控木馬 | G86: -
A87: 85 | B87: domain | C87: sbido.com | D87: - | E87: - | F87: 遠控木馬 | G87: -
A88: 86 | B88: ip | C88: 199.247.29.25 | D88: 荷蘭 | E88: - | F88: APT | G88: 摩訶草
A89: 87 | B89: ip | C89: 194.87.108.94 | D89: 波蘭 | E89: - | F89: APT | G89: 海蓮花
A90: 88 | B90: ip | C90: 45.41.105.49 | D90: 緬甸 | E90: 仰光 | F90: 遠控木馬 | G90: -
A91: 89 | B91: ip | C91: 175.41.145.5 | D91: 新加坡 | E91: 新加坡 | F91: 僵屍網絡 | G91: -
A92: 90 | B92: ip | C92: 45.227.254.34 | D92: 立陶宛 | E92: 維爾紐斯 | F92: 漏洞利用 | G92: -
A93: 91 | B93: ip | C93: 31.3.152.100 | D93: 瑞典 | E93: 斯德哥爾摩 | F93: 僵屍網絡 | G93: -
A94: 92 | B94: ip | C94: 129.212.255.222 | D94: 美國 | E94: 森尼韋爾 | F94: 僵屍網絡 | G94: -
... A107: 105 | B107: domain | C107: dsguiwejbvysui.cn | D107: - | E107: - | F107: 遠控木馬 | G107: -
A108: 106 | B108: domain | C108: www.yyy16888.vip | D108: - | E108: - | F108: 遠控木馬
A109: 107 | B109: domain | C109: english-studies.net | D109: - | E109: - | F109: 遠控木馬 | G109: -
A110: 108 | B110: domain | C110: labelectechnology.com | D110: - | E110: - | F110: 遠控木馬 | G110: -
A111: 109 | B111: domain | C111: 2miners.com | D111: - | E111: - | F111: 挖礦木馬 | G111: -
A112: 110 | B112: domain | C112: truthink.in | D112: - | E112: - | F112: 遠控木馬 | G112: -
A113: 111 | B113: domain | C113: xiaoshihou40.org | D113: - | E113: - | F113: 遠控木馬 | G113: -
A114: 112 | B114: domain | C114: xiaoshihou37.org | D114: - | E114: - | F114: 遠控木馬 | G114: -
A115: 113 | B115: domain | C115: irusl.atlastimber.shop | D115: - | E115: - | F115: 遠控木馬 | G115: -
A116: 114 | B116: domain | C116: shunlissll.com | D116: - | E116: - | F116: 遠控木馬 | G116: -
A117: 115 | B117: domain | C117: shunshunlilixxsc.com | D117: - | E117: - | F117: 遠控木馬 | G117: -
A118: 116 | B118: domain | C118: ll.0z1zxmvo.com | D118: - | E118: - | F118: 遠控木馬 | G118: -
A119: 117 | B119: domain | C119: cdn.openroute.dev | D119: - | E119: - | F119: 遠控木馬 | G119: -
A120: 118 | B120: ip | C120: 52.167.144.232 | D120: 美國 | E120: 弗吉尼亞海灘 | F120: 僵屍網絡 | G120: 僵屍網絡
... A209: 207 | B209: domain | C209: ct.feliz.icu | D209: - | E209: - | F209: 遠控木馬 | G209: -
B210: 數據支撐機構：HKCSI
B211: 數據整編機構：CTIWG技術支持團隊（香港網絡安全研究院）
B212: 數據問題溝通：ctiwg@hkcsi.hk
B213: 上述IP建議在網絡邊界封禁

Sheet 涉香港金融行業釣魚網站
A1: 涉香港金融行業釣魚網站
A2: 序號 | B2: 釣魚網站URL | C2: 涉及目標 | D2: 提交機構
A3: 1 | B3: mabanquereunion.bnpparibas/ | C3: 金融機構 | D3: WBZX
A4: 2 | B4: d318d6p1c4tjb9.cloudfront.net/h5/#/login | C4: 金融機構 | D4: WBZX
A5: 3 | B5: ht717.ensemble98.top/h5/#/login | C5: 金融機構 | D5: WBZX
A6: 4 | B6: hui.pvkkp29.cn/#/pages/login/login | C6: 金融機構 | D6: WBZX
A7: 5 | B7: wap.ouboo.top/%E6%AC%A2%E8%BF%8E%E4%BD%BF%E7%94%A8_files/welcome.html | C7: 金融機構 | D7: WBZX
A8: 6 | B8: flux.ouboo.top/%E6%AC%A2%E8%BF%8E%E4%BD%BF%E7%94%A8_files/welcome.html | C8: 金融機構 | D8: WBZX
A9: 7 | B9: 156.247.41.16/%E6%AC%A2%E8%BF%8E%E4%BD%BF%E7%94%A8_files/welcome.html | C9: 金融機構 | D9: WBZX
A10: 8 | B10: dh.ouboo.top/%E6%AC%A2%E8%BF%8E%E4%BD%BF%E7%94%A8_files/welcome.html | C10: 金融機構 | D10: WBZX
A11: 9 | B11: hshcgold.com/%E6%AC%A2%E8%BF%8E%E4%BD%BF%E7%94%A8_files/welcome.html | C11: 金融機構 | D11: WBZX
A12: 10 | B12: 31.57.51.16/%E6%AC%A2%E8%BF%8E%E4%BD%BF%E7%94%A8_files/welcome.html | C12: 金融機構 | D12: WBZX
A13: 11 | B13: presse.realestate.bnpparibas.fr/ | C13: 金融機構 | D13: WBZX
A14: 12 | B14: 43.198.203.201/login | C14: 金融機構 | D14: WBZX
... A90: 88 | B90: hfvip.net/login | C90: 金融機構 | D90: WBZX
